Workbook

Sheet Dashboard
A1: E-commerce Performance Dashboard
A2: Order data 2020-10-29 → 2025-12-01 · Realised sales = Completed + Returned orders · Amounts in currency units as recorded
A4: Net revenue | E4: Refunds (approved) | I4: Orders | M4: Repeat rate (90d) | Q4: Orders with payment issue | U4: Est. loss on below-cost sales
A5: =SUMIFS(Curated_Items!$S$5:$S$771,Curated_Items!$T$5:$T$771,1) -> 19164568 | E5: =SUMIFS(Curated_Items!$Q$5:$Q$771,Curated_Items!$T$5:$T$771,1) -> 815331.14 | I5: =SUMPRODUCT((Curated_Items!$T$5:$T$771=1)/COUNTIFS(Curated_Items!$B$5:$B$771,Curated_Items!$B$5:$B$771)) -> 223 | M5: =KPI7_Repeat_Rate!B6 -> 0.091836735 | Q5: =COUNTIF(KPI8_Payment_Recon!H5:H332,"<>OK") -> 218 | U5: =KPI9_Margin_Risk!C7 -> 1795100.8
A7: Net revenue by month (KPI 1) | M7: Net revenue by category (KPI 1)
A25: Net revenue by channel, 2024–25 (KPI 4) | M25: Average order value by segment (KPI 3)
A43: Top 10 customers by net LTV (KPI 2) | M43: Top 10 supplier composite score (KPI 6)
A61: Product return rate — highest 10 (KPI 5) | M61: Payment reconciliation flags (KPI 8)
A80: Key assumptions: see Assumptions_README sheet. Dashboard tiles and KPI 1 are live formulas on Curated_Items; other KPI tables are pipeline outputs (pipeline.py) with formulas for totals, scores and MoM.

Sheet KPI1_Net_Revenue
A1: KPI 1 · Net revenue by product category, per month
A2: Net revenue = line revenue after discount − approved refunds, attributed to ORDER month. Only Completed + Returned orders (Cancelled/Pending excluded). Live SUMIFS on Curated_Items.
A4: Month | B4: Electronics | C4: Fashion | D4: Grocery | E4: Home & Kitchen | F4: Sports | G4: Unknown | H4: Total
A5: 2020-10 | B5: =SUMIFS(Curated_Items!$S$5:$S$771,Curated_Items!$D$5:$D$771,$A5,Curated_Items!$H$5:$H$771,B$4,Curated_Items!$T$5:$T$771,1) -> 0 | C5: =SUMIFS(Curated_Items!$S$5:$S$771,Curated_Items!$D$5:$D$771,$A5,Curated_Items!$H$5:$H$771,C$4,Curated_Items!$T$5:$T$771,1) -> 0 | D5: =SUMIFS(Curated_Items!$S$5:$S$771,Curated_Items!$D$5:$D$771,$A5,Curated_Items!$H$5:$H$771,D$4,Curated_Items!$T$5:$T$771,1) -> 45144.5 | E5: =SUMIFS(Curated_Items!$S$5:$S$771,Curated_Items!$D$5:$D$771,$A5,Curated_Items!$H$5:$H$771,E$4,Curated_Items!$T$5:$T$771,1) -> 0 | F5: =SUMIFS(Curated_Items!$S$5:$S$771,Curated_Items!$D$5:$D$771,$A5,Curated_Items!$H$5:$H$771,F$4,Curated_Items!$T$5:$T$771,1) -> 0 | G5: =SUMIFS(Curated_Items!$S$5:$S$771,Curated_Items!$D$5:$D$771,$A5,Curated_Items!$H$5:$H$771,G$4,Curated_Items!$T$5:$T$771,1) -> 0 | H5: =SUM(B5:G5) -> 45144.5
A6: 2020-12 | B6: =SUMIFS(Curated_Items!$S$5:$S$771,Curated_Items!$D$5:$D$771,$A6,Curated_Items!$H$5:$H$771,B$4,Curated_Items!$T$5:$T$771,1) -> 0 | C6: =SUMIFS(Curated_Items!$S$5:$S$771,Curated_Items!$D$5:$D$771,$A6,Curated_Items!$H$5:$H$771,C$4,Curated_Items!$T$5:$T$771,1) -> 0 | D6: =SUMIFS(Curated_Items!$S$5:$S$771,Curated_Items!$D$5:$D$771,$A6,Curated_Items!$H$5:$H$771,D$4,Curated_Items!$T$5:$T$771,1) -> 0 | E6: =SUMIFS(Curated_Items!$S$5:$S$771,Curated_Items!$D$5:$D$771,$A6,Curated_Items!$H$5:$H$771,E$4,Curated_Items!$T$5:$T$771,1) -> 21122.18 | F6: =SUMIFS(Curated_Items!$S$5:$S$771,Curated_Items!$D$5:$D$771,$A6,Curated_Items!$H$5:$H$771,F$4,Curated_Items!$T$5:$T$771,1) -> 0 | G6: =SUMIFS(Curated_Items!$S$5:$S$771,Curated_Items!$D$5:$D$771,$A6,Curated_Items!$H$5:$H$771,G$4,Curated_Items!$T$5:$T$771,1) -> 0 | H6: =SUM(B6:G6) -> 21122.18
A7: 2021-05 | B7: =SUMIFS(Curated_Items!$S$5:$S$771,Curated_Items!$D$5:$D$771,$A7,Curated_Items!$H$5:$H$771,B$4,Curated_Items!$T$5:$T$771,1) -> 16084.14 | C7: =SUMIFS(Curated_Items!$S$5:$S$771,Curated_Items!$D$5:$D$771,$A7,Curated_Items!$H$5:$H$771,C$4,Curated_Items!$T$5:$T$771,1) -> 0 | D7: =SUMIFS(Curated_Items!$S$5:$S$771,Curated_Items!$D$5:$D$771,$A7,Curated_Items!$H$5:$H$771,D$4,Curated_Items!$T$5:$T$771,1) -> 88376.89 | E7: =SUMIFS(Curated_Items!$S$5:$S$771,Curated_Items!$D$5:$D$771,$A7,Curated_Items!$H$5:$H$771,E$4,Curated_Items!$T$5:$T$771,1) -> 0 | F7: =SUMIFS(Curated_Items!$S$5:$S$771,Curated_Items!$D$5:$D$771,$A7,Curated_Items!$H$5:$H$771,F$4,Curated_Items!$T$5:$T$771,1) -> 0 | G7: =SUMIFS(Curated_Items!$S$5:$S$771,Curated_Items!$D$5:$D$771,$A7,Curated_Items!$H$5:$H$771,G$4,Curated_Items!$T$5:$T$771,1) -> 0 | H7: =SUM(B7:G7) -> 104461.03
A8: 2021-09 | B8: =SUMIFS(Curated_Items!$S$5:$S$771,Curated_Items!$D$5:$D$771,$A8,Curated_Items!$H$5:$H$771,B$4,Curated_Items!$T$5:$T$771,1) -> 0 | C8: =SUMIFS(Curated_Items!$S$5:$S$771,Curated_Items!$D$5:$D$771,$A8,Curated_Items!$H$5:$H$771,C$4,Curated_Items!$T$5:$T$771,1) -> 0 | D8: =SUMIFS(Curated_Items!$S$5:$S$771,Curated_Items!$D$5:$D$771,$A8,Curated_Items!$H$5:$H$771,D$4,Curated_Items!$T$5:$T$771,1) -> 13037.07 | E8: =SUMIFS(Curated_Items!$S$5:$S$771,Curated_Items!$D$5:$D$771,$A8,Curated_Items!$H$5:$H$771,E$4,Curated_Items!$T$5:$T$771,1) -> 56241.65 | F8: =SUMIFS(Curated_Items!$S$5:$S$771,Curated_Items!$D$5:$D$771,$A8,Curated_Items!$H$5:$H$771,F$4,Curated_Items!$T$5:$T$771,1) -> 0 | G8: =SUMIFS(Curated_Items!$S$5:$S$771,Curated_Items!$D$5:$D$771,$A8,Curated_Items!$H$5:$H$771,G$4,Curated_Items!$T$5:$T$771,1) -> 0 | H8: =SUM(B8:G8) -> 69278.72
A9: 2022-10 | B9: =SUMIFS(Curated_Items!$S$5:$S$771,Curated_Items!$D$5:$D$771,$A9,Curated_Items!$H$5:$H$771,B$4,Curated_Items!$T$5:$T$771,1) -> 0 | C9: =SUMIFS(Curated_Items!$S$5:$S$771,Curated_Items!$D$5:$D$771,$A9,Curated_Items!$H$5:$H$771,C$4,Curated_Items!$T$5:$T$771,1) -> 9607.25 | D9: =SUMIFS(Curated_Items!$S$5:$S$771,Curated_Items!$D$5:$D$771,$A9,Curated_Items!$H$5:$H$771,D$4,Curated_Items!$T$5:$T$771,1) -> 17582.77 | E9: =SUMIFS(Curated_Items!$S$5:$S$771,Curated_Items!$D$5:$D$771,$A9,Curated_Items!$H$5:$H$771,E$4,Curated_Items!$T$5:$T$771,1) -> 0 | F9: =SUMIFS(Curated_Items!$S$5:$S$771,Curated_Items!$D$5:$D$771,$A9,Curated_Items!$H$5:$H$771,F$4,Curated_Items!$T$5:$T$771,1) -> 81924.16 | G9: =SUMIFS(Curated_Items!$S$5:$S$771,Curated_Items!$D$5:$D$771,$A9,Curated_Items!$H$5:$H$771,G$4,Curated_Items!$T$5:$T$771,1) -> 0 | H9: =SUM(B9:G9) -> 109114.18
A10: 2024-01 | B10: =SUMIFS(Curated_Items!$S$5:$S$771,Curated_Items!$D$5:$D$771,$A10,Curated_Items!$H$5:$H$771,B$4,Curated_Items!$T$5:$T$771,1) -> 154568.75 | C10: =SUMIFS(Curated_Items!$S$5:$S$771,Curated_Items!$D$5:$D$771,$A10,Curated_Items!$H$5:$H$771,C$4,Curated_Items!$T$5:$T$771,1) -> 70908.67 | D10: =SUMIFS(Curated_Items!$S$5:$S$771,Curated_Items!$D$5:$D$771,$A10,Curated_Items!$H$5:$H$771,D$4,Curated_Items!$T$5:$T$771,1) -> 212099.87 | E10: =SUMIFS(Curated_Items!$S$5:$S$771,Curated_Items!$D$5:$D$771,$A10,Curated_Items!$H$5:$H$771,E$4,Curated_Items!$T$5:$T$771,1) -> 235968.07 | F10: =SUMIFS(Curated_Items!$S$5:$S$771,Curated_Items!$D$5:$D$771,$A10,Curated_Items!$H$5:$H$771,F$4,Curated_Items!$T$5:$T$771,1) -> 33174.22 | G10: =SUMIFS(Curated_Items!$S$5:$S$771,Curated_Items!$D$5:$D$771,$A10,Curated_Items!$H$5:$H$771,G$4,Curated_Items!$T$5:$T$771,1) -> 0 | H10: =SUM(B10:G10) -> 706719.58
A11: 2024-02 | B11: =SUMIFS(Curated_Items!$S$5:$S$771,Curated_Items!$D$5:$D$771,$A11,Curated_Items!$H$5:$H$771,B$4,Curated_Items!$T$5:$T$771,1) -> 117501.07 | C11: =SUMIFS(Curated_Items!$S$5:$S$771,Curated_Items!$D$5:$D$771,$A11,Curated_Items!$H$5:$H$771,C$4,Curated_Items!$T$5:$T$771,1) -> 336016.22 | D11: =SUMIFS(Curated_Items!$S$5:$S$771,Curated_Items!$D$5:$D$771,$A11,Curated_Items!$H$5:$H$771,D$4,Curated_Items!$T$5:$T$771,1) -> 105096.8 | E11: =SUMIFS(Curated_Items!$S$5:$S$771,Curated_Items!$D$5:$D$771,$A11,Curated_Items!$H$5:$H$771,E$4,Curated_Items!$T$5:$T$771,1) -> 141153.75 | F11: =SUMIFS(Curated_Items!$S$5:$S$771,Curated_Items!$D$5:$D$771,$A11,Curated_Items!$H$5:$H$771,F$4,Curated_Items!$T$5:$T$771,1) -> 60151.91 | G11: =SUMIFS(Curated_Items!$S$5:$S$771,Curated_Items!$D$5:$D$771,$A11,Curated_Items!$H$5:$H$771,G$4,Curated_Items!$T$5:$T$771,1) -> 0 | H11: =SUM(B11:G11) -> 759919.75
A12: 2024-03 | B12: =SUMIFS(Curated_Items!$S$5:$S$771,Curated_Items!$D$5:$D$771,$A12,Curated_Items!$H$5:$H$771,B$4,Curated_Items!$T$5:$T$771,1) -> 106461.26 | C12: =SUMIFS(Curated_Items!$S$5:$S$771,Curated_Items!$D$5:$D$771,$A12,Curated_Items!$H$5:$H$771,C$4,Curated_Items!$T$5:$T$771,1) -> 243040.65 | D12: =SUMIFS(Curated_Items!$S$5:$S$771,Curated_Items!$D$5:$D$771,$A12,Curated_Items!$H$5:$H$771,D$4,Curated_Items!$T$5:$T$771,1) -> 285106.27 | E12: =SUMIFS(Curated_Items!$S$5:$S$771,Curated_Items!$D$5:$D$771,$A12,Curated_Items!$H$5:$H$771,E$4,Curated_Items!$T$5:$T$771,1) -> 183928.33 | F12: =SUMIFS(Curated_Items!$S$5:$S$771,Curated_Items!$D$5:$D$771,$A12,Curated_Items!$H$5:$H$771,F$4,Curated_Items!$T$5:$T$771,1) -> 77531.86 | G12: =SUMIFS(Curated_Items!$S$5:$S$771,Curated_Items!$D$5:$D$771,$A12,Curated_Items!$H$5:$H$771,G$4,Curated_Items!$T$5:$T$771,1) -> 0 | H12: =SUM(B12:G12) -> 896068.37
A13: 2024-04 | B13: =SUMIFS(Curated_Items!$S$5:$S$771,Curated_Items!$D$5:$D$771,$A13,Curated_Items!$H$5:$H$771,B$4,Curated_Items!$T$5:$T$771,1) -> 95577.03 | C13: =SUMIFS(Curated_Items!$S$5:$S$771,Curated_Items!$D$5:$D$771,$A13,Curated_Items!$H$5:$H$771,C$4,Curated_Items!$T$5:$T$771,1) -> 106497.74 | D13: =SUMIFS(Curated_Items!$S$5:$S$771,Curated_Items!$D$5:$D$771,$A13,Curated_Items!$H$5:$H$771,D$4,Curated_Items!$T$5:$T$771,1) -> 34155.34 | E13: =SUMIFS(Curated_Items!$S$5:$S$771,Curated_Items!$D$5:$D$771,$A13,Curated_Items!$H$5:$H$771,E$4,Curated_Items!$T$5:$T$771,1) -> 118109.27 | F13: =SUMIFS(Curated_Items!$S$5:$S$771,Curated_Items!$D$5:$D$771,$A13,Curated_Items!$H$5:$H$771,F$4,Curated_Items!$T$5:$T$771,1) -> 175708.52 | G13: =SUMIFS(Curated_Items!$S$5:$S$771,Curated_Items!$D$5:$D$771,$A13,Curated_Items!$H$5:$H$771,G$4,Curated_Items!$T$5:$T$771,1) -> 0 | H13: =SUM(B13:G13) -> 530047.9
A14: 2024-05 | B14: =SUMIFS(Curated_Items!$S$5:$S$771,Curated_Items!$D$5:$D$771,$A14,Curated_Items!$H$5:$H$771,B$4,Curated_Items!$T$5:$T$771,1) -> 87407.72 | C14: =SUMIFS(Curated_Items!$S$5:$S$771,Curated_Items!$D$5:$D$771,$A14,Curated_Items!$H$5:$H$771,C$4,Curated_Items!$T$5:$T$771,1) -> 207823.27 | D14: =SUMIFS(Curated_Items!$S$5:$S$771,Curated_Items!$D$5:$D$771,$A14,Curated_Items!$H$5:$H$771,D$4,Curated_Items!$T$5:$T$771,1) -> 52748.3 | E14: =SUMIFS(Curated_Items!$S$5:$S$771,Curated_Items!$D$5:$D$771,$A14,Curated_Items!$H$5:$H$771,E$4,Curated_Items!$T$5:$T$771,1) -> 158595.93 | F14: =SUMIFS(Curated_Items!$S$5:$S$771,Curated_Items!$D$5:$D$771,$A14,Curated_Items!$H$5:$H$771,F$4,Curated_Items!$T$5:$T$771,1) -> 46075.44 | G14: =SUMIFS(Curated_Items!$S$5:$S$771,Curated_Items!$D$5:$D$771,$A14,Curated_Items!$H$5:$H$771,G$4,Curated_Items!$T$5:$T$771,1) -> 0 | H14: =SUM(B14:G14) -> 552650.66
A15: 2024-06 | B15: =SUMIFS(Curated_Items!$S$5:$S$771,Curated_Items!$D$5:$D$771,$A15,Curated_Items!$H$5:$H$771,B$4,Curated_Items!$T$5:$T$771,1) -> 66132.8 | C15: =SUMIFS(Curated_Items!$S$5:$S$771,Curated_Items!$D$5:$D$771,$A15,Curated_Items!$H$5:$H$771,C$4,Curated_Items!$T$5:$T$771,1) -> 427275.13 | D15: =SUMIFS(Curated_Items!$S$5:$S$771,Curated_Items!$D$5:$D$771,$A15,Curated_Items!$H$5:$H$771,D$4,Curated_Items!$T$5:$T$771,1) -> 437611.63 | E15: =SUMIFS(Curated_Items!$S$5:$S$771,Curated_Items!$D$5:$D$771,$A15,Curated_Items!$H$5:$H$771,E$4,Curated_Items!$T$5:$T$771,1) -> 272902.43 | F15: =SUMIFS(Curated_Items!$S$5:$S$771,Curated_Items!$D$5:$D$771,$A15,Curated_Items!$H$5:$H$771,F$4,Curated_Items!$T$5:$T$771,1) -> 185970.02 | G15: =SUMIFS(Curated_Items!$S$5:$S$771,Curated_Items!$D$5:$D$771,$A15,Curated_Items!$H$5:$H$771,G$4,Curated_Items!$T$5:$T$771,1) -> 0 | H15: =SUM(B15:G15) -> 1389892
A16: 2024-07 | B16: =SUMIFS(Curated_Items!$S$5:$S$771,Curated_Items!$D$5:$D$771,$A16,Curated_Items!$H$5:$H$771,B$4,Curated_Items!$T$5:$T$771,1) -> 41429.58 | C16: =SUMIFS(Curated_Items!$S$5:$S$771,Curated_Items!$D$5:$D$771,$A16,Curated_Items!$H$5:$H$771,C$4,Curated_Items!$T$5:$T$771,1) -> 116679.51 | D16: =SUMIFS(Curated_Items!$S$5:$S$771,Curated_Items!$D$5:$D$771,$A16,Curated_Items!$H$5:$H$771,D$4,Curated_Items!$T$5:$T$771,1) -> 105216.93 | E16: =SUMIFS(Curated_Items!$S$5:$S$771,Curated_Items!$D$5:$D$771,$A16,Curated_Items!$H$5:$H$771,E$4,Curated_Items!$T$5:$T$771,1) -> 247681.29 | F16: =SUMIFS(Curated_Items!$S$5:$S$771,Curated_Items!$D$5:$D$771,$A16,Curated_Items!$H$5:$H$771,F$4,Curated_Items!$T$5:$T$771,1) -> 66447.79 | G16: =SUMIFS(Curated_Items!$S$5:$S$771,Curated_Items!$D$5:$D$771,$A16,Curated_Items!$H$5:$H$771,G$4,Curated_Items!$T$5:$T$771,1) -> 18998.55 | H16: =SUM(B16:G16) -> 596453.65
... A32: 2025-12 | B32: =SUMIFS(Curated_Items!$S$5:$S$771,Curated_Items!$D$5:$D$771,$A32,Curated_Items!$H$5:$H$771,B$4,Curated_Items!$T$5:$T$771,1) -> 15383.27 | C32: =SUMIFS(Curated_Items!$S$5:$S$771,Curated_Items!$D$5:$D$771,$A32,Curated_Items!$H$5:$H$771,C$4,Curated_Items!$T$5:$T$771,1) -> 17597.06 | D32: =SUMIFS(Curated_Items!$S$5:$S$771,Curated_Items!$D$5:$D$771,$A32,Curated_Items!$H$5:$H$771,D$4,Curated_Items!$T$5:$T$771,1) -> 0 | E32: =SUMIFS(Curated_Items!$S$5:$S$771,Curated_Items!$D$5:$D$771,$A32,Curated_Items!$H$5:$H$771,E$4,Curated_Items!$T$5:$T$771,1) -> 3308 | F32: =SUMIFS(Curated_Items!$S$5:$S$771,Curated_Items!$D$5:$D$771,$A32,Curated_Items!$H$5:$H$771,F$4,Curated_Items!$T$5:$T$771,1) -> 101394.45 | G32: =SUMIFS(Curated_Items!$S$5:$S$771,Curated_Items!$D$5:$D$771,$A32,Curated_Items!$H$5:$H$771,G$4,Curated_Items!$T$5:$T$771,1) -> 0 | H32: =SUM(B32:G32) -> 137682.78
A33: Total | B33: =SUM(B5:B32) -> 2569374.4 | C33: =SUM(C5:C32) -> 4024835.6 | D33: =SUM(D5:D32) -> 4920588.5 | E33: =SUM(E5:E32) -> 4834145.2 | F33: =SUM(F5:F32) -> 2677280.6 | G33: =SUM(G5:G32) -> 138343.58 | H33: =SUM(H5:H32) -> 19164568
A34: Check vs pipeline | H34: 19164568
A35: Difference | H35: =H33-H34 -> 0

Sheet KPI2_Top_Customers
A1: KPI 2 · Top 10 customers by net lifetime value
A2: Completed orders only, net of approved refunds. Orders with unknown customer (key −1) cannot be attributed and are excluded from the ranking; their value is shown as a memo line.
A4: rank | B4: customer_id | C4: full_name | D4: customer_segment | E4: city | F4: orders | G4: gross_spend | H4: refunds | I4: net_ltv
A5: 1 | B5: C0118 | C5: Utkarsh Bhat | D5: Gold | E5: Hyderabad | F5: 3 | G5: 532447.01 | H5: 0 | I5: 532447.01
A6: 2 | B6: C0107 | C6: Eesha Sethi | D6: Silver | E6: Kolkata | F6: 2 | G6: 463604.51 | H6: 0 | I6: 463604.51
A7: 3 | B7: C0061 | C7: Yadavi Bhakta | D7: Platinum | E7: Chennai | F7: 2 | G7: 341730.61 | H7: 0 | I7: 341730.61
A8: 4 | B8: C0148 | C8: Ucchal Thaker | D8: Bronze | E8: Jaipur | F8: 3 | G8: 329199.63 | H8: 0 | I8: 329199.63
A9: 5 | B9: C0142 | C9: Zansi Prasad | D9: Platinum | E9: Ahmedabad | F9: 4 | G9: 328510.35 | H9: 0 | I9: 328510.35
A10: 6 | B10: C0001 | C10: Isaac Bakshi | D10: Bronze | E10: Bangalore | F10: 4 | G10: 377880.04 | H10: 75816.05 | I10: 302063.99
A11: 7 | B11: C0085 | C11: Chakrika Koshy | D11: Silver | E11: Chennai | F11: 3 | G11: 291047.36 | H11: 0 | I11: 291047.36
A12: 8 | B12: C0033 | C12: Hamsini Rao | D12: Gold | E12: Lucknow | F12: 2 | G12: 268013.97 | H12: 0 | I12: 268013.97
A13: 9 | B13: C0129 | C13: Siddharth Bains | D13: Platinum | E13: New Delhi | F13: 3 | G13: 284905.07 | H13: 19128.89 | I13: 265776.18
A14: 10 | B14: C0037 | C14: Gautam Rana | D14: Gold | E14: Jaipur | F14: 2 | G14: 259380.42 | H14: 0 | I14: 259380.42
A16: Memo: completed-order net revenue with unknown customer (excluded) | I16: 562442.51

Sheet KPI3_Segments
A1: KPI 3 · Standardized customer segment profile
A2: customer_count = customers in the dimension per segment (placeholder UNKNOWN row excluded). AOV = completed-order net revenue ÷ distinct completed orders for customers in that segment.
A4: segment | B4: customer_count | C4: ordering_customers | D4: orders | E4: revenue | F4: avg_order_value
A5: Bronze | B5: 36 | C5: 22 | D5: 36 | E5: 2747177.5 | F5: 76310.488
A6: Gold | B6: 38 | C6: 21 | D6: 33 | E6: 3234111.4 | F6: 98003.375
A7: Platinum | B7: 44 | C7: 30 | D7: 51 | E7: 4083493.4 | F7: 80068.499
A8: Silver | B8: 40 | C8: 25 | D8: 36 | E8: 3204268.1 | F8: 89007.448
A9: Total | B9: =SUM(B5:B8) -> 158 | C9: =SUM(C5:C8) -> 98 | D9: =SUM(D5:D8) -> 156 | E9: =SUM(E5:E8) -> 13269050 | F9: =E9/D9 -> 85058.016

Sheet KPI4_MoM_by_Channel
A1: KPI 4 · Month-over-month order volume & net revenue growth by channel
A2: Window: LAG() over month within channel (SQL equivalent in README). Dense window Jan-2024 → Dec-2025 (7 orders before 2024 are too sparse for MoM). MoM shows "n/a" when the prior month is zero. Net revenue as per KPI 1.
A4: Channel | B4: Month | C4: Orders | D4: Net revenue | E4: Orders MoM % | F4: Net revenue MoM % | I4: Month | J4: App | K4: Store | L4: Web
A5: App | B5: 2024-01 | C5: 6 | D5: 506719.81 | E5: n/a | F5: n/a | I5: 2024-01 | J5: =D5 -> 506719.81 | K5: =D29 -> 77292.09 | L5: =D53 -> 122707.68
A6: App | B6: 2024-02 | C6: 3 | D6: 328038.05 | E6: =IF(C5>0,C6/C5-1,"n/a") -> -0.5 | F6: =IF(D5>0,D6/D5-1,"n/a") -> -0.35262438 | I6: 2024-02 | J6: =D6 -> 328038.05 | K6: =D30 -> 176780.78 | L6: =D54 -> 255100.92
A7: App | B7: 2024-03 | C7: 5 | D7: 340581.28 | E7: =IF(C6>0,C7/C6-1,"n/a") -> 0.66666667 | F7: =IF(D6>0,D7/D6-1,"n/a") -> 0.038237119 | I7: 2024-03 | J7: =D7 -> 340581.28 | K7: =D31 -> 336137.86 | L7: =D55 -> 219349.23
A8: App | B8: 2024-04 | C8: 3 | D8: 272281.13 | E8: =IF(C7>0,C8/C7-1,"n/a") -> -0.4 | F8: =IF(D7>0,D8/D7-1,"n/a") -> -0.20053994 | I8: 2024-04 | J8: =D8 -> 272281.13 | K8: =D32 -> 22580.5 | L8: =D56 -> 235186.27
A9: App | B9: 2024-05 | C9: 2 | D9: 248097.95 | E9: =IF(C8>0,C9/C8-1,"n/a") -> -0.33333333 | F9: =IF(D8>0,D9/D8-1,"n/a") -> -0.088816952 | I9: 2024-05 | J9: =D9 -> 248097.95 | K9: =D33 -> 304552.71 | L9: =D57 -> 0
A10: App | B10: 2024-06 | C10: 9 | D10: 684406.22 | E10: =IF(C9>0,C10/C9-1,"n/a") -> 3.5 | F10: =IF(D9>0,D10/D9-1,"n/a") -> 1.758613 | I10: 2024-06 | J10: =D10 -> 684406.22 | K10: =D34 -> 563769.51 | L10: =D58 -> 141716.28
A11: App | B11: 2024-07 | C11: 5 | D11: 218621.63 | E11: =IF(C10>0,C11/C10-1,"n/a") -> -0.44444444 | F11: =IF(D10>0,D11/D10-1,"n/a") -> -0.68056744 | I11: 2024-07 | J11: =D11 -> 218621.63 | K11: =D35 -> 134606.36 | L11: =D59 -> 243225.66
A12: App | B12: 2024-08 | C12: 1 | D12: 60641.05 | E12: =IF(C11>0,C12/C11-1,"n/a") -> -0.8 | F12: =IF(D11>0,D12/D11-1,"n/a") -> -0.722621 | I12: 2024-08 | J12: =D12 -> 60641.05 | K12: =D36 -> 293046.3 | L12: =D60 -> 755648.42
A13: App | B13: 2024-09 | C13: 1 | D13: 190124.75 | E13: =IF(C12>0,C13/C12-1,"n/a") -> 0 | F13: =IF(D12>0,D13/D12-1,"n/a") -> 2.1352483 | I13: 2024-09 | J13: =D13 -> 190124.75 | K13: =D37 -> 633815.95 | L13: =D61 -> 360672.5
A14: App | B14: 2024-10 | C14: 3 | D14: 274270.91 | E14: =IF(C13>0,C14/C13-1,"n/a") -> 2 | F14: =IF(D13>0,D14/D13-1,"n/a") -> 0.44258394 | I14: 2024-10 | J14: =D14 -> 274270.91 | K14: =D38 -> 122920.6 | L14: =D62 -> 196517.69
A15: App | B15: 2024-11 | C15: 9 | D15: 953580.21 | E15: =IF(C14>0,C15/C14-1,"n/a") -> 2 | F15: =IF(D14>0,D15/D14-1,"n/a") -> 2.4767822 | I15: 2024-11 | J15: =D15 -> 953580.21 | K15: =D39 -> 499132.45 | L15: =D63 -> 0
A16: App | B16: 2024-12 | C16: 2 | D16: 254049.75 | E16: =IF(C15>0,C16/C15-1,"n/a") -> -0.77777778 | F16: =IF(D15>0,D16/D15-1,"n/a") -> -0.73358324 | I16: 2024-12 | J16: =D16 -> 254049.75 | K16: =D40 -> 322813.04 | L16: =D64 -> 305686.57
A17: App | B17: 2025-01 | C17: 4 | D17: 323432.52 | E17: =IF(C16>0,C17/C16-1,"n/a") -> 1 | F17: =IF(D16>0,D17/D16-1,"n/a") -> 0.27310702 | I17: 2025-01 | J17: =D17 -> 323432.52 | K17: =D41 -> 331101.22 | L17: =D65 -> 386589.1
... A28: App | B28: 2025-12 | C28: 0 | D28: 0 | E28: =IF(C27>0,C28/C27-1,"n/a") -> n/a | F28: =IF(D27>0,D28/D27-1,"n/a") -> n/a | I28: 2025-12 | J28: =D28 -> 0 | K28: =D52 -> 0 | L28: =D76 -> 137682.78
A29: Store | B29: 2024-01 | C29: 2 | D29: 77292.09 | E29: n/a | F29: n/a
A30: Store | B30: 2024-02 | C30: 2 | D30: 176780.78 | E30: =IF(C29>0,C30/C29-1,"n/a") -> 0 | F30: =IF(D29>0,D30/D29-1,"n/a") -> 1.2871782
A31: Store | B31: 2024-03 | C31: 4 | D31: 336137.86 | E31: =IF(C30>0,C31/C30-1,"n/a") -> 1 | F31: =IF(D30>0,D31/D30-1,"n/a") -> 0.90143895
A32: Store | B32: 2024-04 | C32: 1 | D32: 22580.5 | E32: =IF(C31>0,C32/C31-1,"n/a") -> -0.75 | F32: =IF(D31>0,D32/D31-1,"n/a") -> -0.93282369
A33: Store | B33: 2024-05 | C33: 4 | D33: 304552.71 | E33: =IF(C32>0,C33/C32-1,"n/a") -> 3 | F33: =IF(D32>0,D33/D32-1,"n/a") -> 12.487421
A34: Store | B34: 2024-06 | C34: 4 | D34: 563769.51 | E34: =IF(C33>0,C34/C33-1,"n/a") -> 0 | F34: =IF(D33>0,D34/D33-1,"n/a") -> 0.85113936
A35: Store | B35: 2024-07 | C35: 1 | D35: 134606.36 | E35: =IF(C34>0,C35/C34-1,"n/a") -> -0.75 | F35: =IF(D34>0,D35/D34-1,"n/a") -> -0.76123867
A36: Store | B36: 2024-08 | C36: 3 | D36: 293046.3 | E36: =IF(C35>0,C36/C35-1,"n/a") -> 2 | F36: =IF(D35>0,D36/D35-1,"n/a") -> 1.1770613
A37: Store | B37: 2024-09 | C37: 8 | D37: 633815.95 | E37: =IF(C36>0,C37/C36-1,"n/a") -> 1.6666667 | F37: =IF(D36>0,D37/D36-1,"n/a") -> 1.1628526
A38: Store | B38: 2024-10 | C38: 2 | D38: 122920.6 | E38: =IF(C37>0,C38/C37-1,"n/a") -> -0.75 | F38: =IF(D37>0,D38/D37-1,"n/a") -> -0.80606263
A39: Store | B39: 2024-11 | C39: 7 | D39: 499132.45 | E39: =IF(C38>0,C39/C38-1,"n/a") -> 2.5 | F39: =IF(D38>0,D39/D38-1,"n/a") -> 3.0606086
A40: Store | B40: 2024-12 | C40: 2 | D40: 322813.04 | E40: =IF(C39>0,C40/C39-1,"n/a") -> -0.71428571 | F40: =IF(D39>0,D40/D39-1,"n/a") -> -0.35325175
A41: Store | B41: 2025-01 | C41: 4 | D41: 331101.22 | E41: =IF(C40>0,C41/C40-1,"n/a") -> 1 | F41: =IF(D40>0,D41/D40-1,"n/a") -> 0.025674861
... A52: Store | B52: 2025-12 | C52: 0 | D52: 0 | E52: =IF(C51>0,C52/C51-1,"n/a") -> n/a | F52: =IF(D51>0,D52/D51-1,"n/a") -> n/a
A53: Web | B53: 2024-01 | C53: 1 | D53: 122707.68 | E53: n/a | F53: n/a
A54: Web | B54: 2024-02 | C54: 3 | D54: 255100.92 | E54: =IF(C53>0,C54/C53-1,"n/a") -> 2 | F54: =IF(D53>0,D54/D53-1,"n/a") -> 1.078932
A55: Web | B55: 2024-03 | C55: 2 | D55: 219349.23 | E55: =IF(C54>0,C55/C54-1,"n/a") -> -0.33333333 | F55: =IF(D54>0,D55/D54-1,"n/a") -> -0.14014724
A56: Web | B56: 2024-04 | C56: 4 | D56: 235186.27 | E56: =IF(C55>0,C56/C55-1,"n/a") -> 1 | F56: =IF(D55>0,D56/D55-1,"n/a") -> 0.072200117
A57: Web | B57: 2024-05 | C57: 0 | D57: 0 | E57: =IF(C56>0,C57/C56-1,"n/a") -> -1 | F57: =IF(D56>0,D57/D56-1,"n/a") -> -1
A58: Web | B58: 2024-06 | C58: 3 | D58: 141716.28 | E58: =IF(C57>0,C58/C57-1,"n/a") -> n/a | F58: =IF(D57>0,D58/D57-1,"n/a") -> n/a
A59: Web | B59: 2024-07 | C59: 5 | D59: 243225.66 | E59: =IF(C58>0,C59/C58-1,"n/a") -> 0.66666667 | F59: =IF(D58>0,D59/D58-1,"n/a") -> 0.71628595
A60: Web | B60: 2024-08 | C60: 5 | D60: 755648.42 | E60: =IF(C59>0,C60/C59-1,"n/a") -> 0 | F60: =IF(D59>0,D60/D59-1,"n/a") -> 2.1067792
A61: Web | B61: 2024-09 | C61: 2 | D61: 360672.5 | E61: =IF(C60>0,C61/C60-1,"n/a") -> -0.6 | F61: =IF(D60>0,D61/D60-1,"n/a") -> -0.522698
A62: Web | B62: 2024-10 | C62: 3 | D62: 196517.69 | E62: =IF(C61>0,C62/C61-1,"n/a") -> 0.5 | F62: =IF(D61>0,D62/D61-1,"n/a") -> -0.45513537
A63: Web | B63: 2024-11 | C63: 0 | D63: 0 | E63: =IF(C62>0,C63/C62-1,"n/a") -> -1 | F63: =IF(D62>0,D63/D62-1,"n/a") -> -1
A64: Web | B64: 2024-12 | C64: 4 | D64: 305686.57 | E64: =IF(C63>0,C64/C63-1,"n/a") -> n/a | F64: =IF(D63>0,D64/D63-1,"n/a") -> n/a
A65: Web | B65: 2025-01 | C65: 4 | D65: 386589.1 | E65: =IF(C64>0,C65/C64-1,"n/a") -> 0 | F65: =IF(D64>0,D65/D64-1,"n/a") -> 0.26465844
... A76: Web | B76: 2025-12 | C76: 1 | D76: 137682.78 | E76: =IF(C75>0,C76/C75-1,"n/a") -> n/a | F76: =IF(D75>0,D76/D75-1,"n/a") -> n/a

Sheet KPI5_Return_Rate
A1: KPI 5 · Product return rate — top 10 and bottom 10
A2: Return rate = returned qty ÷ ordered qty (Completed+Returned lines). Returned qty = full line quantity of APPROVED returns (the returns table has no partial quantities). Minimum volume threshold: 30 ordered units (19 of 69 products qualify). Ties broken by higher volume.
A4: Top 10 highest return rate
A5: product_id | B5: product_name | C5: category | D5: ordered_qty | E5: returned_qty | F5: return_rate
A6: P040 | B6: Footwear Item 40 | C6: Fashion | D6: 31 | E6: 5 | F6: 0.16129032
A7: P021 | B7: Fitness Item 21 | C7: Sports | D7: 35 | E7: 5 | F7: 0.14285714
A8: P042 | B8: Staples Item 42 | C8: Grocery | D8: 31 | E8: 3 | F8: 0.096774194
A9: P065 | B9: Footwear Item 65 | C9: Fashion | D9: 44 | E9: 4 | F9: 0.090909091
A10: P044 | B10: Beverages Item 44 | C10: Grocery | D10: 30 | E10: 1 | F10: 0.033333333
A11: P049 | B11: Beverages Item 49 | C11: Grocery | D11: 32 | E11: 1 | F11: 0.03125
A12: P007 | B12: Outdoor Item 7 | C12: Sports | D12: 36 | E12: 1 | F12: 0.027777778
A13: P054 | B13: Fitness Item 54 | C13: Sports | D13: 37 | E13: 1 | F13: 0.027027027
A14: P061 | B14: Furniture Item 61 | C14: Home & Kitchen | D14: 51 | E14: 0 | F14: 0
A15: P031 | B15: Accessories Item 31 | C15: Electronics | D15: 43 | E15: 0 | F15: 0
A17: Bottom 10 lowest return rate
A18: product_id | B18: product_name | C18: category | D18: ordered_qty | E18: returned_qty | F18: return_rate
A19: P061 | B19: Furniture Item 61 | C19: Home & Kitchen | D19: 51 | E19: 0 | F19: 0
A20: P031 | B20: Accessories Item 31 | C20: Electronics | D20: 43 | E20: 0 | F20: 0
A21: P012 | B21: Menswear Item 12 | C21: Fashion | D21: 40 | E21: 0 | F21: 0
A22: P068 | B22: Staples Item 68 | C22: Grocery | D22: 37 | E22: 0 | F22: 0
A23: P002 | B23: Furniture Item 2 | C23: Home & Kitchen | D23: 33 | E23: 0 | F23: 0
A24: P016 | B24: Footwear Item 16 | C24: Fashion | D24: 32 | E24: 0 | F24: 0
A25: P041 | B25: Cookware Item 41 | C25: Home & Kitchen | D25: 32 | E25: 0 | F25: 0
A26: P055 | B26: Staples Item 55 | C26: Grocery | D26: 32 | E26: 0 | F26: 0
A27: P004 | B27: Appliances Item 4 | C27: Home & Kitchen | D27: 30 | E27: 0 | F27: 0
A28: P037 | B28: Mobiles Item 37 | C28: Electronics | D28: 30 | E28: 0 | F28: 0

Sheet KPI6_Supplier_Scorecard
A1: KPI 6 · Supplier performance scorecard
A2: Composite (0–100) = 40% revenue (min-max) + 30% return performance (1 − min-max of avg product return rate) + 30% quality (rating_normalized ÷ 5). Ratings given on a 0–10 scale (raw > 5) were halved. Weights are inputs (blue) – scores recalculate.
A3: Weights: | C3: Revenue | D3: 0.4 | E3: Returns | F3: 0.3 | G3: Quality | H3: 0.3
A5: Rank | B5: Supplier | C5: ID | D5: Country | E5: Rating (raw) | F5: Rating (norm. /5) | G5: Products sold | H5: Net revenue | I5: Avg product return rate | J5: Revenue score | K5: Return score | L5: Composite score
A6: 1 | B6: Biswas, Karpe And Radhakrishnan | C6: S007 | D6: Unknown | E6: 4.2 | F6: 4.2 | G6: 6 | H6: 1861322.7 | I6: 0 | J6: =IF(MAX($H$6:$H$23)>MIN($H$6:$H$23),(H6-MIN($H$6:$H$23))/(MAX($H$6:$H$23)-MIN($H$6:$H$23)),0) -> 0.81831668 | K6: =IF(MAX($I$6:$I$23)>MIN($I$6:$I$23),1-(I6-MIN($I$6:$I$23))/(MAX($I$6:$I$23)-MIN($I$6:$I$23)),1) -> 1 | L6: =100*($D$3*J6+$F$3*K6+$H$3*F6/5) -> 87.932667
A7: 2 | B7: Lalla, Ganesh And Oommen | C7: S006 | D7: Germany | E7: 7.5 | F7: 3.75 | G7: 8 | H7: 2223174.1 | I7: 0.025718391 | J7: =IF(MAX($H$6:$H$23)>MIN($H$6:$H$23),(H7-MIN($H$6:$H$23))/(MAX($H$6:$H$23)-MIN($H$6:$H$23)),0) -> 1 | K7: =IF(MAX($I$6:$I$23)>MIN($I$6:$I$23),1-(I7-MIN($I$6:$I$23))/(MAX($I$6:$I$23)-MIN($I$6:$I$23)),1) -> 0.83926006 | L7: =100*($D$3*J7+$F$3*K7+$H$3*F7/5) -> 87.677802
A8: 3 | B8: Chaudhari, Sandal And Desai | C8: S015 | D8: India | E8: 4.1 | F8: 4.1 | G8: 4 | H8: 1821770.4 | I8: 0.022727273 | J8: =IF(MAX($H$6:$H$23)>MIN($H$6:$H$23),(H8-MIN($H$6:$H$23))/(MAX($H$6:$H$23)-MIN($H$6:$H$23)),0) -> 0.79845776 | K8: =IF(MAX($I$6:$I$23)>MIN($I$6:$I$23),1-(I8-MIN($I$6:$I$23))/(MAX($I$6:$I$23)-MIN($I$6:$I$23)),1) -> 0.85795455 | L8: =100*($D$3*J8+$F$3*K8+$H$3*F8/5) -> 82.276947
A9: 4 | B9: Amble, Prashad And Jha | C9: S004 | D9: Unknown | E9: 9.4 | F9: 4.7 | G9: 4 | H9: 1612831.4 | I9: 0.065247253 | J9: =IF(MAX($H$6:$H$23)>MIN($H$6:$H$23),(H9-MIN($H$6:$H$23))/(MAX($H$6:$H$23)-MIN($H$6:$H$23)),0) -> 0.69355078 | K9: =IF(MAX($I$6:$I$23)>MIN($I$6:$I$23),1-(I9-MIN($I$6:$I$23))/(MAX($I$6:$I$23)-MIN($I$6:$I$23)),1) -> 0.59220467 | L9: =100*($D$3*J9+$F$3*K9+$H$3*F9/5) -> 73.708171
A10: 5 | B10: Dhar-Gopal | C10: S005 | D10: Germany | E10: 4.5 | F10: 4.5 | G10: 2 | H10: 910835.68 | I10: 0 | J10: =IF(MAX($H$6:$H$23)>MIN($H$6:$H$23),(H10-MIN($H$6:$H$23))/(MAX($H$6:$H$23)-MIN($H$6:$H$23)),0) -> 0.3410832 | K10: =IF(MAX($I$6:$I$23)>MIN($I$6:$I$23),1-(I10-MIN($I$6:$I$23))/(MAX($I$6:$I$23)-MIN($I$6:$I$23)),1) -> 1 | L10: =100*($D$3*J10+$F$3*K10+$H$3*F10/5) -> 70.643328
A11: 6 | B11: Baral, Din And Bhalla | C11: S001 | D11: Unknown | E11: 4.3 | F11: 4.3 | G11: 3 | H11: 1336183.9 | I11: 0.070987654 | J11: =IF(MAX($H$6:$H$23)>MIN($H$6:$H$23),(H11-MIN($H$6:$H$23))/(MAX($H$6:$H$23)-MIN($H$6:$H$23)),0) -> 0.55464786 | K11: =IF(MAX($I$6:$I$23)>MIN($I$6:$I$23),1-(I11-MIN($I$6:$I$23))/(MAX($I$6:$I$23)-MIN($I$6:$I$23)),1) -> 0.55632716 | L11: =100*($D$3*J11+$F$3*K11+$H$3*F11/5) -> 64.675729
A12: 7 | B12: Amble, Virk And Dalal | C12: S018 | D12: Vietnam | E12: 5 | F12: 5 | G12: 4 | H12: 615765.99 | I12: 0.022727273 | J12: =IF(MAX($H$6:$H$23)>MIN($H$6:$H$23),(H12-MIN($H$6:$H$23))/(MAX($H$6:$H$23)-MIN($H$6:$H$23)),0) -> 0.19293058 | K12: =IF(MAX($I$6:$I$23)>MIN($I$6:$I$23),1-(I12-MIN($I$6:$I$23))/(MAX($I$6:$I$23)-MIN($I$6:$I$23)),1) -> 0.85795455 | L12: =100*($D$3*J12+$F$3*K12+$H$3*F12/5) -> 63.455859
A13: 8 | B13: Saini, Doctor And Char | C13: S009 | D13: Germany | E13: 4 | F13: 4 | G13: 2 | H13: 657783.34 | I13: 0 | J13: =IF(MAX($H$6:$H$23)>MIN($H$6:$H$23),(H13-MIN($H$6:$H$23))/(MAX($H$6:$H$23)-MIN($H$6:$H$23)),0) -> 0.21402722 | K13: =IF(MAX($I$6:$I$23)>MIN($I$6:$I$23),1-(I13-MIN($I$6:$I$23))/(MAX($I$6:$I$23)-MIN($I$6:$I$23)),1) -> 1 | L13: =100*($D$3*J13+$F$3*K13+$H$3*F13/5) -> 62.561089
A14: 9 | B14: Bahl, Mander And Chada | C14: S003 | D14: Vietnam | E14: 2.9 | F14: 2.9 | G14: 4 | H14: 870624.82 | I14: 0 | J14: =IF(MAX($H$6:$H$23)>MIN($H$6:$H$23),(H14-MIN($H$6:$H$23))/(MAX($H$6:$H$23)-MIN($H$6:$H$23)),0) -> 0.32089358 | K14: =IF(MAX($I$6:$I$23)>MIN($I$6:$I$23),1-(I14-MIN($I$6:$I$23))/(MAX($I$6:$I$23)-MIN($I$6:$I$23)),1) -> 1 | L14: =100*($D$3*J14+$F$3*K14+$H$3*F14/5) -> 60.235743
A15: 10 | B15: Raj-Palla | C15: S014 | D15: Unknown | E15: 2.5 | F15: 2.5 | G15: 5 | H15: 1166889.1 | I15: 0.019354839 | J15: =IF(MAX($H$6:$H$23)>MIN($H$6:$H$23),(H15-MIN($H$6:$H$23))/(MAX($H$6:$H$23)-MIN($H$6:$H$23)),0) -> 0.46964597 | K15: =IF(MAX($I$6:$I$23)>MIN($I$6:$I$23),1-(I15-MIN($I$6:$I$23))/(MAX($I$6:$I$23)-MIN($I$6:$I$23)),1) -> 0.87903226 | L15: =100*($D$3*J15+$F$3*K15+$H$3*F15/5) -> 60.156806
A16: 11 | B16: Babu And Sons | C16: S008 | D16: India | E16: 3.7 | F16: 3.7 | G16: 2 | H16: 611245.71 | I16: 0 | J16: =IF(MAX($H$6:$H$23)>MIN($H$6:$H$23),(H16-MIN($H$6:$H$23))/(MAX($H$6:$H$23)-MIN($H$6:$H$23)),0) -> 0.19066097 | K16: =IF(MAX($I$6:$I$23)>MIN($I$6:$I$23),1-(I16-MIN($I$6:$I$23))/(MAX($I$6:$I$23)-MIN($I$6:$I$23)),1) -> 1 | L16: =100*($D$3*J16+$F$3*K16+$H$3*F16/5) -> 59.826439
A17: 12 | B17: Zacharia, Agarwal And Sankar | C17: S012 | D17: Vietnam | E17: 3 | F17: 3 | G17: 5 | H17: 1387406.7 | I17: 0.080520613 | J17: =IF(MAX($H$6:$H$23)>MIN($H$6:$H$23),(H17-MIN($H$6:$H$23))/(MAX($H$6:$H$23)-MIN($H$6:$H$23)),0) -> 0.58036649 | K17: =IF(MAX($I$6:$I$23)>MIN($I$6:$I$23),1-(I17-MIN($I$6:$I$23))/(MAX($I$6:$I$23)-MIN($I$6:$I$23)),1) -> 0.49674617 | L17: =100*($D$3*J17+$F$3*K17+$H$3*F17/5) -> 56.117045
... A23: 18 | B23: Rege, Kurian And Gulati | C23: S017 | D23: Vietnam | E23: 2.7 | F23: 2.7 | G23: 1 | H23: 231513.82 | I23: 0.16 | J23: =IF(MAX($H$6:$H$23)>MIN($H$6:$H$23),(H23-MIN($H$6:$H$23))/(MAX($H$6:$H$23)-MIN($H$6:$H$23)),0) -> 0 | K23: =IF(MAX($I$6:$I$23)>MIN($I$6:$I$23),1-(I23-MIN($I$6:$I$23))/(MAX($I$6:$I$23)-MIN($I$6:$I$23)),1) -> 0 | L23: =100*($D$3*J23+$F$3*K23+$H$3*F23/5) -> 16.2

Sheet KPI7_Repeat_Rate
A1: KPI 7 · Customer repeat-purchase rate (90 days)
A2: Share of customers with ≥1 additional distinct completed order within 90 days of their first completed order. Customers with unknown key excluded. "Eligible" excludes customers whose 90-day window had not yet closed at the data end date.
A4: Customers with ≥1 completed order | B4: 98
A5: Repeat buyers (≤90 days) | B5: 9
A6: Repeat-purchase rate (all customers) | B6: =B5/B4 -> 0.091836735
A8: Customers with a closed 90-day window | B8: 93
A9: Repeat buyers among those | B9: 8
A10: Repeat-purchase rate (eligible only) | B10: =B9/B8 -> 0.086021505
A12: Data end date: 2025-12-01

Sheet KPI8_Payment_Recon
A1: KPI 8 · Payment reconciliation & anomaly report
A2: Order total = Σ line net_amount (all statuses). Paid = Σ payments with status Success. Variance beyond ±1 flags Under/Over-payment. Flags can combine. Orders in payments but absent from FACT_ORDERS are "Orphan".
A4: Order | B4: Status | C4: Order total | D4: Payment rows | E4: Success rows | F4: Paid (Success) | G4: Payment statuses | H4: Flag | I4: Variance | K4: Flag | L4: Orders
A5: O00001 | B5: Completed | C5: 109114.18 | D5: 1 | E5: 1 | F5: 109114.18 | G5: Success | H5: OK | I5: =IF(ISNUMBER(C5),F5-C5,"n/a") -> 0 | K5: OK | L5: =COUNTIF($H$5:$H$332,"*"&K5&"*") -> 110
A6: O00002 | B6: Cancelled | C6: 21724.64 | D6: 1 | E6: 0 | F6: 0 | G6: Refunded | H6: No successful payment | I6: =IF(ISNUMBER(C6),F6-C6,"n/a") -> -21724.64 | K6: No successful payment | L6: =COUNTIF($H$5:$H$332,"*"&K6&"*") -> 88
A7: O00003 | B7: Completed | C7: 33974.88 | D7: 1 | E7: 0 | F7: 0 | G7: Pending | H7: No successful payment | I7: =IF(ISNUMBER(C7),F7-C7,"n/a") -> -33974.88 | K7: Underpaid | L7: =COUNTIF($H$5:$H$332,"*"&K7&"*") -> 46
A8: O00004 | B8: Completed | C8: 180629.84 | D8: 1 | E8: 1 | F8: 180629.84 | G8: Success | H8: OK | I8: =IF(ISNUMBER(C8),F8-C8,"n/a") -> 0 | K8: Overpaid | L8: =COUNTIF($H$5:$H$332,"*"&K8&"*") -> 40
A9: O00005 | B9: Completed | C9: 104397.68 | D9: 1 | E9: 1 | F9: 73078.38 | G9: Success | H9: Underpaid | I9: =IF(ISNUMBER(C9),F9-C9,"n/a") -> -31319.3 | K9: Paid but order Cancelled | L9: =COUNTIF($H$5:$H$332,"*"&K9&"*") -> 35
A10: O00006 | B10: Completed | C10: 17880.99 | D10: 1 | E10: 1 | F10: 17880.99 | G10: Success | H10: OK | I10: =IF(ISNUMBER(C10),F10-C10,"n/a") -> 0 | K10: Orphan payment (order not in FACT_ORDERS) | L10: =COUNTIF($H$5:$H$332,"*"&K10&"*") -> 10
A11: O00007 | B11: Completed | C11: 57672.52 | D11: 1 | E11: 1 | F11: 57672.52 | G11: Success | H11: OK | I11: =IF(ISNUMBER(C11),F11-C11,"n/a") -> 0 | K11: No payment row | L11: =COUNTIF($H$5:$H$332,"*"&K11&"*") -> 8
A12: O00008 | B12: Completed | C12: 141201.64 | D12: 1 | E12: 1 | F12: 168821.36 | G12: Success | H12: Overpaid | I12: =IF(ISNUMBER(C12),F12-C12,"n/a") -> 27619.72 | K12: Conflicting payment statuses | L12: =COUNTIF($H$5:$H$332,"*"&K12&"*") -> 5
A13: O00009 | B13: Completed | C13: 40778.86 | D13: 1 | E13: 0 | F13: 0 | G13: Refunded | H13: No successful payment | I13: =IF(ISNUMBER(C13),F13-C13,"n/a") -> -40778.86
A14: O00010 | B14: Completed | C14: 168178.45 | D14: 1 | E14: 1 | F14: 168178.45 | G14: Success | H14: OK | I14: =IF(ISNUMBER(C14),F14-C14,"n/a") -> 0
A15: O00011 | B15: Completed | C15: 43233.87 | D15: 1 | E15: 1 | F15: 43233.87 | G15: Success | H15: OK | I15: =IF(ISNUMBER(C15),F15-C15,"n/a") -> 0
A16: O00012 | B16: Completed | C16: 141177.62 | D16: 1 | E16: 0 | F16: 0 | G16: Failed | H16: No successful payment | I16: =IF(ISNUMBER(C16),F16-C16,"n/a") -> -141177.62
A17: O00013 | B17: Completed | C17: 25431.4 | D17: 1 | E17: 0 | F17: 0 | G17: Failed | H17: No successful payment | I17: =IF(ISNUMBER(C17),F17-C17,"n/a") -> -25431.4
A18: O00014 | B18: Returned | C18: 139604.32 | D18: 1 | E18: 1 | F18: 156502.06 | G18: Success | H18: Overpaid | I18: =IF(ISNUMBER(C18),F18-C18,"n/a") -> 16897.74
A19: O00015 | B19: Completed | C19: 130237.17 | D19: 1 | E19: 1 | F19: 130237.17 | G19: Success | H19: OK | I19: =IF(ISNUMBER(C19),F19-C19,"n/a") -> 0
A20: O00016 | B20: Cancelled | C20: 80420.7 | D20: 1 | E20: 0 | F20: 0 | G20: Refunded | H20: No successful payment | I20: =IF(ISNUMBER(C20),F20-C20,"n/a") -> -80420.7
A21: O00017 | B21: Completed | C21: 27430.41 | D21: 0 | E21: 0 | F21: 0 | H21: No payment row | I21: =IF(ISNUMBER(C21),F21-C21,"n/a") -> -27430.41
A22: O00018 | B22: Returned | C22: 188218.14 | D22: 1 | E22: 1 | F22: 131752.7 | G22: Success | H22: Underpaid | I22: =IF(ISNUMBER(C22),F22-C22,"n/a") -> -56465.44
A23: O00019 | B23: Pending | C23: 140291.34 | D23: 0 | E23: 0 | F23: 0 | H23: No payment row | I23: =IF(ISNUMBER(C23),F23-C23,"n/a") -> -140291.34
A24: O00020 | B24: Completed | C24: 161580.74 | D24: 1 | E24: 1 | F24: 210054.96 | G24: Success | H24: Overpaid | I24: =IF(ISNUMBER(C24),F24-C24,"n/a") -> 48474.22
A25: O00021 | B25: Pending | C25: 29190.88 | D25: 1 | E25: 0 | F25: 0 | G25: Refunded | H25: No successful payment | I25: =IF(ISNUMBER(C25),F25-C25,"n/a") -> -29190.88
A26: O00022 | B26: Cancelled | C26: 11854.78 | D26: 1 | E26: 1 | F26: 5927.39 | G26: Success | H26: Underpaid; Paid but order Cancelled | I26: =IF(ISNUMBER(C26),F26-C26,"n/a") -> -5927.39
A27: O00023 | B27: Completed | C27: 22602.06 | D27: 1 | E27: 0 | F27: 0 | G27: Failed | H27: No successful payment | I27: =IF(ISNUMBER(C27),F27-C27,"n/a") -> -22602.06
A28: O00024 | B28: Completed | C28: 98196.55 | D28: 1 | E28: 1 | F28: 98196.55 | G28: Success | H28: OK | I28: =IF(ISNUMBER(C28),F28-C28,"n/a") -> 0
A29: O00025 | B29: Completed | C29: 64052.43 | D29: 1 | E29: 1 | F29: 64052.43 | G29: Success | H29: OK | I29: =IF(ISNUMBER(C29),F29-C29,"n/a") -> 0
A30: O00026 | B30: Returned | C30: 74805.15 | D30: 1 | E30: 1 | F30: 74805.15 | G30: Success | H30: OK | I30: =IF(ISNUMBER(C30),F30-C30,"n/a") -> 0
A31: O00027 | B31: Cancelled | C31: 58166.47 | D31: 1 | E31: 1 | F31: 58166.47 | G31: Success | H31: Paid but order Cancelled | I31: =IF(ISNUMBER(C31),F31-C31,"n/a") -> 0
A32: O00028 | B32: Completed | C32: 134660.86 | D32: 1 | E32: 1 | F32: 67330.43 | G32: Success | H32: Underpaid | I32: =IF(ISNUMBER(C32),F32-C32,"n/a") -> -67330.43
A33: O00029 | B33: Cancelled | C33: 87102.46 | D33: 1 | E33: 1 | F33: 113233.2 | G33: Success | H33: Overpaid; Paid but order Cancelled | I33: =IF(ISNUMBER(C33),F33-C33,"n/a") -> 26130.74
A34: O00030 | B34: Pending | C34: 135193.83 | D34: 1 | E34: 1 | F34: 143687.55 | G34: Success | H34: Overpaid | I34: =IF(ISNUMBER(C34),F34-C34,"n/a") -> 8493.72
A35: O00031 | B35: Returned | C35: 102935.09 | D35: 1 | E35: 1 | F35: 102734.51 | G35: Success | H35: Underpaid | I35: =IF(ISNUMBER(C35),F35-C35,"n/a") -> -200.58
... A43: O00039 | B43: Completed | C43: 32157.81 | D43: 1 | E43: 1 | F43: 54738.31 | G43: Success | H43: Overpaid | I43: =IF(ISNUMBER(C43),F43-C43,"n/a") -> 22580.5
A44: O00040 | B44: Completed | C44: 107969.1 | D44: 0 | E44: 0 | F44: 0 | H44: No payment row | I44: =IF(ISNUMBER(C44),F44-C44,"n/a") -> -107969.1
A45: O00041 | B45: Completed | C45: 88663.82 | D45: 1 | E45: 0 | F45: 0 | G45: Failed | H45: No successful payment | I45: =IF(ISNUMBER(C45),F45-C45,"n/a") -> -88663.82
A46: O00042 | B46: Completed | C46: 31749.05 | D46: 1 | E46: 1 | F46: 27686.04 | G46: Success | H46: Underpaid | I46: =IF(ISNUMBER(C46),F46-C46,"n/a") -> -4063.01
A47: O00043 | B47: Cancelled | C47: 100493.15 | D47: 2 | E47: 1 | F47: 320939.45 | G47: Pending/Success | H47: Overpaid; Conflicting payment statuses; Paid but order Cancelled | I47: =IF(ISNUMBER(C47),F47-C47,"n/a") -> 220446.3
A48: O00044 | B48: Completed | C48: 70379.66 | D48: 1 | E48: 1 | F48: 70379.66 | G48: Success | H48: OK | I48: =IF(ISNUMBER(C48),F48-C48,"n/a") -> 0
A49: O00045 | B49: Completed | C49: 39842.03 | D49: 1 | E49: 1 | F49: 39842.03 | G49: Success | H49: OK | I49: =IF(ISNUMBER(C49),F49-C49,"n/a") -> 0
A50: O00046 | B50: Completed | C50: 80190.59 | D50: 1 | E50: 1 | F50: 80190.59 | G50: Success | H50: OK | I50: =IF(ISNUMBER(C50),F50-C50,"n/a") -> 0
A51: O00047 | B51: Completed | C51: 49922.85 | D51: 1 | E51: 1 | F51: 49866.55 | G51: Success | H51: Underpaid | I51: =IF(ISNUMBER(C51),F51-C51,"n/a") -> -56.3
A52: O00048 | B52: Completed | C52: 104461.03 | D52: 0 | E52: 0 | F52: 0 | H52: No payment row | I52: =IF(ISNUMBER(C52),F52-C52,"n/a") -> -104461.03
A53: O00049 | B53: Cancelled | C53: 101394.45 | D53: 1 | E53: 0 | F53: 0 | G53: Refunded | H53: No successful payment | I53: =IF(ISNUMBER(C53),F53-C53,"n/a") -> -101394.45
A54: O00050 | B54: Cancelled | C54: 127138.6 | D54: 1 | E54: 1 | F54: 171095.52 | G54: Success | H54: Overpaid; Paid but order Cancelled | I54: =IF(ISNUMBER(C54),F54-C54,"n/a") -> 43956.92
A55: O00051 | B55: Completed | C55: 71135.85 | D55: 1 | E55: 1 | F55: 49795.09 | G55: Success | H55: Underpaid | I55: =IF(ISNUMBER(C55),F55-C55,"n/a") -> -21340.76
A56: O00052 | B56: Pending | C56: 64121.27 | D56: 1 | E56: 0 | F56: 0 | G56: Refunded | H56: No successful payment | I56: =IF(ISNUMBER(C56),F56-C56,"n/a") -> -64121.27
A57: O00053 | B57: Pending | C57: 4010.91 | D57: 1 | E57: 0 | F57: 0 | G57: Pending | H57: No successful payment | I57: =IF(ISNUMBER(C57),F57-C57,"n/a") -> -4010.91
A58: O00054 | B58: Pending | C58: 154521.63 | D58: 1 | E58: 1 | F58: 154521.63 | G58: Success | H58: OK | I58: =IF(ISNUMBER(C58),F58-C58,"n/a") -> 0
A59: O00055 | B59: Returned | C59: 119015.93 | D59: 1 | E59: 0 | F59: 0 | G59: Failed | H59: No successful payment | I59: =IF(ISNUMBER(C59),F59-C59,"n/a") -> -119015.93
A60: O00056 | B60: Pending | C60: 18640.84 | D60: 1 | E60: 1 | F60: 18640.84 | G60: Success | H60: OK | I60: =IF(ISNUMBER(C60),F60-C60,"n/a") -> 0
A61: O00057 | B61: Pending | C61: 4511.74 | D61: 1 | E61: 1 | F61: 4511.74 | G61: Success | H61: OK | I61: =IF(ISNUMBER(C61),F61-C61,"n/a") -> 0
A62: O00058 | B62: Completed | C62: 103794.82 | D62: 1 | E62: 1 | F62: 103794.82 | G62: Success | H62: OK | I62: =IF(ISNUMBER(C62),F62-C62,"n/a") -> 0
A63: O00059 | B63: Returned | C63: 144271.29 | D63: 1 | E63: 0 | F63: 0 | G63: Failed | H63: No successful payment | I63: =IF(ISNUMBER(C63),F63-C63,"n/a") -> -144271.29
A64: O00060 | B64: Completed | C64: 172606.66 | D64: 1 | E64: 1 | F64: 172606.66 | G64: Success | H64: OK | I64: =IF(ISNUMBER(C64),F64-C64,"n/a") -> 0
... A85: O00081 | B85: Completed | C85: 189373.93 | D85: 1 | E85: 0 | F85: 0 | G85: Refunded | H85: No successful payment | I85: =IF(ISNUMBER(C85),F85-C85,"n/a") -> -189373.93
A86: O00082 | B86: Completed | C86: 224837.1 | D86: 0 | E86: 0 | F86: 0 | H86: No payment row | I86: =IF(ISNUMBER(C86),F86-C86,"n/a") -> -224837.1
A87: O00083 | B87: Completed | C87: 53303.95 | D87: 1 | E87: 1 | F87: 53303.95 | G87: Success | H87: OK | I87: =IF(ISNUMBER(C87),F87-C87,"n/a") -> 0
A88: O00084 | B88: Completed | C88: 124400.9 | D88: 1 | E88: 1 | F88: 124119.38 | G88: Success | H88: Underpaid | I88: =IF(ISNUMBER(C88),F88-C88,"n/a") -> -281.52
A89: O00085 | B89: Completed | C89: 217987.79 | D89: 1 | E89: 0 | F89: 0 | G89: Refunded | H89: No successful payment | I89: =IF(ISNUMBER(C89),F89-C89,"n/a") -> -217987.79
A90: O00086 | B90: Completed | C90: 113750.26 | D90: 1 | E90: 1 | F90: 113750.26 | G90: Success | H90: OK | I90: =IF(ISNUMBER(C90),F90-C90,"n/a") -> 0
A91: O00087 | B91: Completed | C91: 78530.15 | D91: 1 | E91: 1 | F91: 39265.07 | G91: Success | H91: Underpaid | I91: =IF(ISNUMBER(C91),F91-C91,"n/a") -> -39265.08
A92: O00088 | B92: Returned | C92: 190335.48 | D92: 1 | E92: 0 | F92: 0 | G92: Pending | H92: No successful payment | I92: =IF(ISNUMBER(C92),F92-C92,"n/a") -> -190335.48
A93: O00089 | B93: Completed | C93: 20278.89 | D93: 1 | E93: 1 | F93: 20278.89 | G93: Success | H93: OK | I93: =IF(ISNUMBER(C93),F93-C93,"n/a") -> 0
A94: O00090 | B94: Returned | C94: 127561.31 | D94: 1 | E94: 1 | F94: 139080.17 | G94: Success | H94: Overpaid | I94: =IF(ISNUMBER(C94),F94-C94,"n/a") -> 11518.86
A95: O00091 | B95: Returned | C95: 128908.95 | D95: 1 | E95: 1 | F95: 128276.3 | G95: Success | H95: Underpaid | I95: =IF(ISNUMBER(C95),F95-C95,"n/a") -> -632.65
A96: O00092 | B96: Completed | C96: 76752.16 | D96: 1 | E96: 0 | F96: 0 | G96: Refunded | H96: No successful payment | I96: =IF(ISNUMBER(C96),F96-C96,"n/a") -> -76752.16
A97: O00093 | B97: Completed | C97: 16201.73 | D97: 1 | E97: 1 | F97: 16201.73 | G97: Success | H97: OK | I97: =IF(ISNUMBER(C97),F97-C97,"n/a") -> 0
A98: O00094 | B98: Returned | C98: 38979.02 | D98: 1 | E98: 1 | F98: 19489.51 | G98: Success | H98: Underpaid | I98: =IF(ISNUMBER(C98),F98-C98,"n/a") -> -19489.51
A99: O00095 | B99: Completed | C99: 133028.67 | D99: 1 | E99: 0 | F99: 0 | G99: Pending | H99: No successful payment | I99: =IF(ISNUMBER(C99),F99-C99,"n/a") -> -133028.67
A100: O00096 | D100: 1 | E100: 0 | F100: 0 | G100: Failed | H100: Orphan payment (order not in FACT_ORDERS) | I100: =IF(ISNUMBER(C100),F100-C100,"n/a") -> n/a
A101: O00097 | B101: Completed | C101: 102114.63 | D101: 1 | E101: 1 | F101: 102114.63 | G101: Success | H101: OK | I101: =IF(ISNUMBER(C101),F101-C101,"n/a") -> 0
A102: O00098 | B102: Pending | C102: 27808.29 | D102: 1 | E102: 1 | F102: 31979.53 | G102: Success | H102: Overpaid | I102: =IF(ISNUMBER(C102),F102-C102,"n/a") -> 4171.24
A103: O00099 | B103: Completed | C103: 47190.36 | D103: 1 | E103: 0 | F103: 0 | G103: Failed | H103: No successful payment | I103: =IF(ISNUMBER(C103),F103-C103,"n/a") -> -47190.36
A104: O00100 | B104: Completed | C104: 72902.75 | D104: 1 | E104: 1 | F104: 72902.75 | G104: Success | H104: OK | I104: =IF(ISNUMBER(C104),F104-C104,"n/a") -> 0
A105: O00101 | B105: Returned | C105: 114108.78 | D105: 1 | E105: 0 | F105: 0 | G105: Failed | H105: No successful payment | I105: =IF(ISNUMBER(C105),F105-C105,"n/a") -> -114108.78
A106: O00102 | B106: Completed | C106: 138312.17 | D106: 1 | E106: 1 | F106: 179805.82 | G106: Success | H106: Overpaid | I106: =IF(ISNUMBER(C106),F106-C106,"n/a") -> 41493.65
A107: O00103 | B107: Completed | C107: 79229.47 | D107: 1 | E107: 0 | F107: 0 | G107: Failed | H107: No successful payment | I107: =IF(ISNUMBER(C107),F107-C107,"n/a") -> -79229.47
A108: O00104 | B108: Completed | C108: 38433.81 | D108: 1 | E108: 1 | F108: 131635.23 | G108: Success | H108: Overpaid | I108: =IF(ISNUMBER(C108),F108-C108,"n/a") -> 93201.42
A109: O00105 | B109: Pending | C109: 34579.89 | D109: 1 | E109: 1 | F109: 44887.01 | G109: Success | H109: Overpaid | I109: =IF(ISNUMBER(C109),F109-C109,"n/a") -> 10307.12
A110: O00106 | B110: Completed | C110: 161566.24 | D110: 1 | E110: 1 | F110: 161566.24 | G110: Success | H110: OK | I110: =IF(ISNUMBER(C110),F110-C110,"n/a") -> 0
A111: O00107 | B111: Cancelled | C111: 107383.73 | D111: 1 | E111: 1 | F111: 107383.73 | G111: Success | H111: Paid but order Cancelled | I111: =IF(ISNUMBER(C111),F111-C111,"n/a") -> 0
A112: O00108 | B112: Completed | C112: 113386.32 | D112: 1 | E112: 1 | F112: 113386.32 | G112: Success | H112: OK | I112: =IF(ISNUMBER(C112),F112-C112,"n/a") -> 0
... A172: O00168 | B172: Completed | C172: 33822.72 | D172: 1 | E172: 1 | F172: 33822.72 | G172: Success | H172: OK | I172: =IF(ISNUMBER(C172),F172-C172,"n/a") -> 0
A173: O00169 | B173: Pending | C173: 107279.68 | D173: 0 | E173: 0 | F173: 0 | H173: No payment row | I173: =IF(ISNUMBER(C173),F173-C173,"n/a") -> -107279.68
A174: O00170 | B174: Completed | C174: 174448.4 | D174: 1 | E174: 0 | F174: 0 | G174: Refunded | H174: No successful payment | I174: =IF(ISNUMBER(C174),F174-C174,"n/a") -> -174448.4
A175: O00171 | B175: Pending | C175: 93071.87 | D175: 1 | E175: 0 | F175: 0 | G175: Failed | H175: No successful payment | I175: =IF(ISNUMBER(C175),F175-C175,"n/a") -> -93071.87
A176: O00172 | B176: Completed | C176: 11630.62 | D176: 1 | E176: 1 | F176: 11630.62 | G176: Success | H176: OK | I176: =IF(ISNUMBER(C176),F176-C176,"n/a") -> 0
A177: O00173 | B177: Completed | C177: 100390.77 | D177: 1 | E177: 1 | F177: 110211.66 | G177: Success | H177: Overpaid | I177: =IF(ISNUMBER(C177),F177-C177,"n/a") -> 9820.89
A178: O00174 | B178: Returned | C178: 85908.79 | D178: 1 | E178: 0 | F178: 0 | G178: Pending | H178: No successful payment | I178: =IF(ISNUMBER(C178),F178-C178,"n/a") -> -85908.79
A179: O00175 | B179: Pending | C179: 36568.25 | D179: 1 | E179: 1 | F179: 36501.39 | G179: Success | H179: Underpaid | I179: =IF(ISNUMBER(C179),F179-C179,"n/a") -> -66.86
A180: O00176 | B180: Completed | C180: 137941.77 | D180: 1 | E180: 0 | F180: 0 | G180: Failed | H180: No successful payment | I180: =IF(ISNUMBER(C180),F180-C180,"n/a") -> -137941.77
A181: O00177 | B181: Cancelled | C181: 11175.62 | D181: 1 | E181: 1 | F181: 11175.62 | G181: Success | H181: Paid but order Cancelled | I181: =IF(ISNUMBER(C181),F181-C181,"n/a") -> 0
A182: O00178 | B182: Returned | C182: 55298.81 | D182: 1 | E182: 1 | F182: 27649.4 | G182: Success | H182: Underpaid | I182: =IF(ISNUMBER(C182),F182-C182,"n/a") -> -27649.41
A183: O00179 | B183: Pending | C183: 91355.03 | D183: 0 | E183: 0 | F183: 0 | H183: No payment row | I183: =IF(ISNUMBER(C183),F183-C183,"n/a") -> -91355.03
A184: O00180 | B184: Pending | C184: 85251.43 | D184: 1 | E184: 0 | F184: 0 | G184: Refunded | H184: No successful payment | I184: =IF(ISNUMBER(C184),F184-C184,"n/a") -> -85251.43
A185: O00181 | B185: Completed | C185: 22580.5 | D185: 1 | E185: 1 | F185: 22580.5 | G185: Success | H185: OK | I185: =IF(ISNUMBER(C185),F185-C185,"n/a") -> 0
A186: O00182 | B186: Completed | C186: 38858.28 | D186: 1 | E186: 1 | F186: 38858.28 | G186: Success | H186: OK | I186: =IF(ISNUMBER(C186),F186-C186,"n/a") -> 0
A187: O00183 | B187: Pending | C187: 28021.66 | D187: 1 | E187: 1 | F187: 34081.99 | G187: Success | H187: Overpaid | I187: =IF(ISNUMBER(C187),F187-C187,"n/a") -> 6060.33
...

Sheet KPI9_Margin_Risk
A1: Stretch · Margin risk report (products sold at a loss)
A2: Line is "at a loss" when unit_price × (1 − discount%) < product cost_price. Revenue exposed = net_amount of those lines; est. loss = (cost − effective price) × qty. Unknown product and zero-price lines excluded.
A4: Lines at a loss | C4: 163 | D4: of 758
A5: Quantity exposed | C5: 505
A6: Revenue exposed | C6: 4088203.4 | D6: =C6/28565694.61 -> 0.14311584 | E6: of margin-eligible revenue
A7: Estimated loss | C7: 1795100.8
A9: product_id | B9: product_name | C9: category | D9: lines | E9: qty_exposed | F9: revenue_exposed | G9: est_loss | H9: avg_cost | I9: avg_eff_price
A10: P065 | B10: Footwear Item 65 | C10: Fashion | D10: 19 | E10: 66 | F10: 936864.71 | G10: 600320.85 | H10: 23290.69 | I10: 14218.09
A11: P013 | B11: Appliances Item 13 | C11: Home & Kitchen | D11: 12 | E11: 27 | F11: 375725.46 | G11: 297667.78 | H11: 24940.49 | I11: 14060.412
A12: P039 | B12: Fitness Item 39 (Revised) | C12: Sports | D12: 7 | E12: 24 | F12: 125100.76 | G12: 224757.08 | H12: 14577.41 | I12: 5236.776
A13: P060 | B13: Staples Item 60 (Revised) | C13: Grocery | D13: 9 | E13: 28 | F13: 301387.3 | G13: 218747.7 | H13: 18576.25 | I13: 10862.541
A14: P001 | B14: Accessories Item 1 (Revised) | C14: Electronics | D14: 6 | E14: 14 | F14: 144986.74 | G14: 90207.796 | H14: 16799.61 | I14: 10305.43
A15: P020 | B15: Beverages Item 20 | C15: Grocery | D15: 15 | E15: 48 | F15: 158467.26 | G15: 89778.188 | H15: 5171.78 | I15: 3307.4587
A16: P028 | B16: Appliances Item 28 | C16: Home & Kitchen | D16: 8 | E16: 20 | F16: 132460.02 | G16: 56691.575 | H16: 9457.58 | I16: 6767.3719
A17: P006 | B17: Furniture Item 6 | C17: Home & Kitchen | D17: 10 | E17: 27 | F17: 71720.4 | G17: 51127.705 | H17: 4549.93 | I17: 2691.3046
A18: P051 | B18: Footwear Item 51 | C18: Fashion | D18: 5 | E18: 12 | F18: 22435.61 | G18: 32462.588 | H18: 4574.85 | I18: 2301.2365
A19: P002 | B19: Furniture Item 2 | C19: Home & Kitchen | D19: 6 | E19: 26 | F19: 212011.47 | G19: 22694.953 | H19: 9027.17 | I19: 8128.7652
A20: P027 | B20: Appliances Item 27 | C20: Home & Kitchen | D20: 4 | E20: 16 | F20: 271265.15 | G20: 20305.572 | H20: 18223.17 | I20: 16954.072
A21: P010 | B21: Accessories Item 10 | C21: Electronics | D21: 10 | E21: 31 | F21: 33517.62 | G21: 20132.847 | H21: 1730.66 | I21: 1072.5636
... A38: P005 | B38: Staples Item 5 | C38: Grocery | D38: 1 | E38: 2 | F38: 28697.52 | G38: 100.54 | H38: 14399.03 | I38: 14348.76

Sheet Data_Profiling
A1: Data profiling & cleansing report
A2: Issues found, rule applied, and before/after counts. "Before/After" = records (or columns) affected before the rule vs remaining after.
A4: Table | B4: Issue found | C4: Rule applied | D4: Before | E4: After
A5: FACT_ORDERS | B5: 16,365 empty spill-over columns (Column1..ColumnN) in the sheet | C5: Dropped all unnamed empty columns | D5: 16384 | E5: 19
A6: FACT_ORDERS | B6: Channel labels (Web/App/Store) checked for case/space variants | C6: Trim + title-case; 3 distinct values remain | D6: 3 | E6: 3
A7: FACT_ORDERS | B7: Order lines with unknown customer (key -1) | C7: Kept for revenue KPIs; excluded from customer-level KPIs (2,3,7); reported separately | D7: 767 | E7: 730
A8: FACT_ORDERS | B8: Order lines with unknown product (key -1) | C8: Kept; category = "Unknown"; excluded from product/supplier KPIs (5,6,9) | D8: 767 | E8: 759
A9: FACT_ORDERS | B9: Order lines with unit_price = 0 | C9: Revenue kept as recorded (0); excluded from margin KPI | D9: 767 | E9: 766
A10: FACT_ORDERS | B10: gross - discount = net integrity check | C10: All rows pass | D10: 767 | E10: 767
A11: FACT_RETURNS | B11: Returns with return date earlier than order date (return_before_order) | C11: Flagged; kept because refunds are attributed to the ORDER month, not the return month | D11: 59 | E11: 59
A12: FACT_RETURNS | B12: Returns with status Rejected / Pending | C12: Excluded: only Approved returns reduce revenue or count as returned quantity | D12: 59 | E12: 28
A13: FACT_RETURNS | B13: Approved returns with NULL refund_amount | C13: Imputed as full line net_amount | D13: 1 | E13: 0
A14: FACT_RETURNS | B14: Refunds larger than the line net_amount | C14: Capped at line net_amount | D14: 4 | E14: 0
A15: DIM_PRODUCTS | B15: Duplicate product_id / conflicting records; "(Revised)" name suffix on 4 products | C15: product_id is unique (0 duplicates); suffix kept as-is, no merge needed | D15: 71 | E15: 71
A16: DIM_PRODUCTS | B16: Category labels | C16: Trim/title-case; 5 real categories + Unknown | D16: 6 | E16: 6
... A23: FACT_PAYMENTS | B23: 10 payment rows (8 orders) reference orders absent from FACT_ORDERS (is_orphan_order = TRUE; customer −1) | C23: Kept and reported as "Orphan payment" in KPI 8 | D23: 10 | E23: 10
A24: FACT_PAYMENTS | B24: 8 orders have no payment row; 88 orders have no Success payment; 5 orders have mixed statuses | C24: Flagged in KPI 8, not corrected
A25: FACT_RETURNS | B25: 29 of 59 returns carry return_before_order = TRUE (return date precedes order date) | C25: Flagged only; refunds attributed to order month so the date conflict does not affect KPIs | D25: 29 | E25: 29
A26: DIM_PRODUCTS | B26: 11 products have cost_price above list unit_price; 3 products have NULL/0 list price | C26: Handled at line level in KPI 9 (effective price vs cost)
A28: Row counts (curated)
A29: Table | B29: Rows
A30: DIM_CUSTOMERS | B30: 159
A31: DIM_SUPPLIERS | B31: 19
A32: DIM_PRODUCTS | B32: 71
A33: DIM_DATE | B33: 2271
A34: FACT_ORDERS | B34: 767
A35: FACT_PAYMENTS | B35: 325
A36: FACT_RETURNS | B36: 59

Sheet Data_Model
A1: Data model (star schema) & SCD approach
A4: Table | B4: Design | C4: Notes
A5: FACT_ORDERS | B5: Grain: order line. FKs → DIM_CUSTOMERS, DIM_PRODUCTS, DIM_DATE (order_date_key). Measures: quantity, unit_price, discount_pct, gross/discount/net amount. Degenerate dims: order_id, channel, order_status. | C5: Unknown member key −1 for orphaned customer/product references
A6: FACT_RETURNS | B6: Grain: return event on an order line. FK → FACT_ORDERS (fact_order_key), DIM_DATE. Measure: refund_amount. | C6: Only Approved rows reduce revenue
A7: FACT_PAYMENTS | B7: Grain: payment attempt. Joins to orders on order_id (degenerate). FK → DIM_CUSTOMERS, DIM_DATE. | C7: is_orphan_order marks payments without a matching order
A8: DIM_CUSTOMERS | B8: SCD Type 2: surrogate customer_key, natural key customer_id, effective_from/effective_to, is_current. Segment/city changes insert a new row and close the old one (effective_to = new effective_from − 1 day). | C8: Currently 1 row per customer (no history yet). Facts store the surrogate key valid at order time; KPIs on current attributes join through customer_id + is_current.
A9: DIM_PRODUCTS | B9: Type 1 (overwrite). FK supplier_key → DIM_SUPPLIERS. Category standardized.
A10: DIM_SUPPLIERS | B10: Type 1. rating_raw kept for audit, rating_normalized on a 0–5 scale.
A11: DIM_DATE | B11: Calendar dimension keyed yyyymmdd; −1 for unknown.
A14: Full DDL: schema.sql (delivered alongside this workbook).

Sheet Assumptions_README
A1: Assumptions, edge-case decisions & trade-offs
A4: # | B4: Assumption / decision
A5: A1 | B5: Realised sales = order_status Completed or Returned. Cancelled and Pending lines are excluded from revenue KPIs (1, 4, 5, 6, 9 uses all lines). KPI 2, 3, 7 use Completed only, as specified.
A6: A2 | B6: Refunds: only Approved returns reduce revenue. Return quantity = full line quantity (no partial-quantity field). NULL refund on an approved return → full line net; refunds above line net are capped.
A7: A3 | B7: Refunds are attributed to the ORDER month (not return month) because 29 of 59 returns have return dates before the order date.
A8: A4 | B8: Unknown customer (key −1, 37 lines): kept in revenue KPIs, excluded from customer KPIs (2, 3, 7); value reported as memo in KPI 2.
A9: A5 | B9: Unknown product (key −1, 8 lines): category "Unknown" in KPI 1; excluded from product and supplier KPIs. No duplicate product_ids exist, so no merge was needed; "(Revised)" names kept as-is.
A10: A6 | B10: KPI 5 threshold: ≥30 ordered units (19 of 69 products qualify; a lower bar lets 1–2 unit products reach 50%+). Tie-break by higher volume. Many products have 0% return, so the bottom 10 is a tie on 0% broken by volume.
A11: A7 | B11: KPI 6 weights 40/30/30 are editable in the sheet. Revenue and return rate min-max scaled across suppliers. Unknown supplier excluded.
A12: A8 | B12: KPI 7: "within 90 days" = ≤90 days from first completed order date, different order_id. Both all-customer and eligible-only (window closed before 2025-12-01) rates shown.
A13: A9 | B13: KPI 8: tolerance ±1 currency unit. Only Success rows count as paid; Refunded/Failed/Pending do not. Cancelled orders with a Success payment are flagged.
A14: A10 | B14: KPI 4: MoM computed on Jan-2024 → Dec-2025 with zero-filled gaps; Nov/Dec-2025 contain very few orders so late growth rates are noisy.
A15: A11 | B15: Source workbook is already a curated star schema (not raw CSVs); "raw → curated" therefore covers structural cleanup (16,365 empty columns), integrity checks and business-rule derivation, not re-keying.
A16: A12 | B16: Trade-off: KPI 1 and dashboard tiles are live formulas; KPIs needing window logic, ranking or multi-table joins are pipeline.py outputs to keep the workbook auditable and fast.

Sheet AI_Usage_Log
A1: AI usage log
A4: Tool | B4: Sample prompt | C4: How output was validated
A5: Claude (Sonnet 5.5) | B5: "Create the dashboard in this Excel and build the 8 KPIs (+ stretch) with data-quality handling." | C5: Profiled every sheet first; reconciled KPI 1 formula total to pipeline total (difference = 0); checked gross−discount=net on all 767 lines; spot-checked order O00001 payment vs order total.
A6: Claude (Sonnet 5.5) | B6: "Resolve return refunds exceeding line net / NULL refunds before computing net revenue." | C6: Counted affected rows (4 capped, 1 imputed) and confirmed no refund > net after the rule.
A7: Claude (Sonnet 5.5) | B7: "Compute supplier composite score with normalized ratings." | C7: Verified rating_normalized = raw/2 when raw>5 for all 3 affected suppliers; score recalculates from editable weights.

Sheet Curated_Items
A1: Curated order-line fact (raw → curated)
A2: One row per order line. Net revenue and the "recognized" flag are live formulas; refunds = Approved returns only (capped at line net). Recognized = Completed + Returned orders (assumption A1).
A4: order_item_id | B4: order_id | C4: order_date | D4: order_month | E4: customer_id | F4: customer_segment | G4: product_id | H4: category | I4: channel | J4: order_status | K4: quantity | L4: unit_price | M4: discount_pct | N4: gross_amount | O4: discount_amount | P4: net_amount | Q4: refund_amt | R4: returned_qty | S4: net_revenue | T4: recognized
A5: OI000001 | B5: O00079 | C5: 45320 | D5: 2024-01 | E5: C0101 | F5: Bronze | G5: P009 | H5: Home & Kitchen | I5: App | J5: Completed | K5: 3 | L5: 26274.11 | M5: 5 | N5: 78822.33 | O5: 3941.12 | P5: 74881.21 | Q5: 0 | R5: 0 | S5: =P5-Q5 -> 74881.21 | T5: =IF(OR(J5="Completed",J5="Returned"),1,0) -> 1
A6: OI000002 | B6: O00079 | C6: 45320 | D6: 2024-01 | E6: C0101 | F6: Bronze | G6: P065 | H6: Fashion | I6: App | J6: Completed | K6: 4 | L6: 15706.03 | M6: 20 | N6: 62824.12 | O6: 12564.82 | P6: 50259.3 | Q6: 41619.4 | R6: 4 | S6: =P6-Q6 -> 8639.9 | T6: =IF(OR(J6="Completed",J6="Returned"),1,0) -> 1
A7: OI000003 | B7: O00079 | C7: 45320 | D7: 2024-01 | E7: C0101 | F7: Bronze | G7: P015 | H7: Sports | I7: App | J7: Completed | K7: 1 | L7: 4516.1 | M7: 5 | N7: 4516.1 | O7: 225.8 | P7: 4290.3 | Q7: 0 | R7: 0 | S7: =P7-Q7 -> 4290.3 | T7: =IF(OR(J7="Completed",J7="Returned"),1,0) -> 1
A8: OI000004 | B8: O00079 | C8: 45320 | D8: 2024-01 | E8: C0101 | F8: Bronze | G8: P023 | H8: Fashion | I8: App | J8: Completed | K8: 5 | L8: 3019.36 | M8: 10 | N8: 15096.8 | O8: 1509.68 | P8: 13587.12 | Q8: 0 | R8: 0 | S8: =P8-Q8 -> 13587.12 | T8: =IF(OR(J8="Completed",J8="Returned"),1,0) -> 1
A9: OI000005 | B9: O00318 | C9: 45807 | D9: 2025-05 | E9: C0142 | F9: Platinum | G9: P070 | H9: Fashion | I9: Store | J9: Completed | K9: 4 | L9: 3962.52 | M9: 10 | N9: 15850.08 | O9: 1585.01 | P9: 14265.07 | Q9: 0 | R9: 0 | S9: =P9-Q9 -> 14265.07 | T9: =IF(OR(J9="Completed",J9="Returned"),1,0) -> 1
A10: OI000006 | B10: O00318 | C10: 45807 | D10: 2025-05 | E10: C0142 | F10: Platinum | G10: P049 | H10: Grocery | I10: Store | J10: Completed | K10: 5 | L10: 12393.99 | M10: 10 | N10: 61969.95 | O10: 6197 | P10: 55772.95 | Q10: 0 | R10: 0 | S10: =P10-Q10 -> 55772.95 | T10: =IF(OR(J10="Completed",J10="Returned"),1,0) -> 1
A11: OI000007 | B11: O00130 | C11: 45477 | D11: 2024-07 | E11: C0139 | F11: Silver | G11: P027 | H11: Home & Kitchen | I11: Store | J11: Pending | K11: 2 | L11: 20550.39 | M11: 0 | N11: 41100.78 | O11: 0 | P11: 41100.78 | Q11: 0 | R11: 0 | S11: =P11-Q11 -> 41100.78 | T11: =IF(OR(J11="Completed",J11="Returned"),1,0) -> 0
A12: OI000008 | B12: O00130 | C12: 45477 | D12: 2024-07 | E12: C0139 | F12: Silver | G12: P018 | H12: Sports | I12: Store | J12: Pending | K12: 5 | L12: 17477.91 | M12: 10 | N12: 87389.55 | O12: 8738.96 | P12: 78650.59 | Q12: 0 | R12: 0 | S12: =P12-Q12 -> 78650.59 | T12: =IF(OR(J12="Completed",J12="Returned"),1,0) -> 0
A13: OI000009 | B13: O00130 | C13: 45477 | D13: 2024-07 | E13: C0139 | F13: Silver | G13: P062 | H13: Home & Kitchen | I13: Store | J13: Pending | K13: 4 | L13: 8493.72 | M13: 5 | N13: 33974.88 | O13: 1698.74 | P13: 32276.14 | Q13: 0 | R13: 0 | S13: =P13-Q13 -> 32276.14 | T13: =IF(OR(J13="Completed",J13="Returned"),1,0) -> 0
A14: OI000010 | B14: O00130 | C14: 45477 | D14: 2024-07 | E14: C0139 | F14: Silver | G14: P063 | H14: Grocery | I14: Store | J14: Pending | K14: 2 | L14: 9269.43 | M14: 5 | N14: 18538.86 | O14: 926.94 | P14: 17611.92 | Q14: 0 | R14: 0 | S14: =P14-Q14 -> 17611.92 | T14: =IF(OR(J14="Completed",J14="Returned"),1,0) -> 0
A15: OI000011 | B15: O00137 | C15: 45860 | D15: 2025-07 | E15: C0060 | F15: Platinum | G15: P049 | H15: Grocery | I15: App | J15: Completed | K15: 5 | L15: 12393.99 | M15: 10 | N15: 61969.95 | O15: 6197 | P15: 55772.95 | Q15: 0 | R15: 0 | S15: =P15-Q15 -> 55772.95 | T15: =IF(OR(J15="Completed",J15="Returned"),1,0) -> 1
A16: OI000012 | B16: O00137 | C16: 45860 | D16: 2025-07 | E16: C0060 | F16: Platinum | G16: P057 | H16: Sports | I16: App | J16: Completed | K16: 1 | L16: 11518.86 | M16: 0 | N16: 11518.86 | O16: 0 | P16: 11518.86 | Q16: 0 | R16: 0 | S16: =P16-Q16 -> 11518.86 | T16: =IF(OR(J16="Completed",J16="Returned"),1,0) -> 1
... A771: OI000796 | B771: O00055 | C771: 45915 | D771: 2025-09 | E771: C0177 | F771: Silver | G771: P069 | H771: Electronics | I771: App | J771: Returned | K771: 2 | L771: 25742.49 | M771: 20 | N771: 51484.98 | O771: 10297 | P771: 41187.98 | Q771: 0 | R771: 0 | S771: =P771-Q771 -> 41187.98 | T771: =IF(OR(J771="Completed",J771="Returned"),1,0) -> 1

Sheet DIM_CUSTOMERS
A1: customer_key | B1: customer_id | C1: full_name | D1: customer_segment | E1: is_active | F1: effective_from | G1: effective_to | H1: is_current | I1: email | J1: phone | K1: city | L1: state | M1: country | N1: signup_date
A2: -1 | B2: UNKNOWN | C2: Unknown customer | D2: Unknown | E2: NO | F2: 1 | G2: 2958465 | H2: =TRUE() -> TRUE
A3: 1 | B3: C0001 | C3: Isaac Bakshi | D3: Bronze | E3: YES | F3: 45008 | G3: 2958465 | H3: =TRUE() -> TRUE | I3: isaac.bakshi1@example.com | J3: 8196001338 | K3: Bangalore | L3: Karnataka | M3: India | N3: 45008
A4: 2 | B4: C0002 | C4: Tanveer Nayar | D4: Gold | E4: YES | F4: 44308 | G4: 2958465 | H4: =TRUE() -> TRUE | I4: tanveer.nayar2@example.com | J4: 9407816184 | K4: Lucknow | L4: Uttar Pradesh | M4: India | N4: 44308
A5: 3 | B5: C0003 | C5: Nicholas Prabhakar | D5: Platinum | E5: YES | F5: 44585 | G5: 2958465 | H5: =TRUE() -> TRUE | I5: nicholas.prabhakar3@example.com | J5: 8327648350 | K5: Jaipur | L5: Rajasthan | M5: India | N5: 44585
A6: 4 | B6: C0004 | C6: Liam Koshy | D6: Bronze | E6: YES | F6: 45012 | G6: 2958465 | H6: =TRUE() -> TRUE | I6: liam.koshy4@example.com | J6: 6532871012 | K6: Kolkata | L6: West Bengal | M6: India | N6: 45012
A7: 5 | B7: C0005 | C7: Harini Choudhury | D7: Gold | E7: YES | F7: 44518 | G7: 2958465 | H7: =TRUE() -> TRUE | I7: harini.choudhury5@example.com | J7: 8281489325 | K7: Bengaluru | L7: Karnataka | M7: India | N7: 44518
A8: 6 | B8: C0006 | C8: Farhan Chada | D8: Platinum | E8: YES | F8: 44997 | G8: 2958465 | H8: =TRUE() -> TRUE | I8: farhan.chada6@example.com | J8: 7824896383 | K8: Jaipur | L8: Rajasthan | M8: India | N8: 44997
A9: 7 | B9: C0007 | C9: Thomas Amble | D9: Gold | E9: YES | F9: 44274 | G9: 2958465 | H9: =TRUE() -> TRUE | I9: thomas.amble7@example.com | J9: 5183473829 | K9: Lucknow | L9: Uttar Pradesh | M9: India | N9: 44274
A10: 8 | B10: C0008 | C10: Guneet Bhat | D10: Bronze | E10: YES | F10: 44637 | G10: 2958465 | H10: =TRUE() -> TRUE | I10: Unknown | J10: 3872624731 | K10: Bengaluru | L10: Karnataka | M10: India | N10: 44637
A11: 9 | B11: C0009 | C11: Daniel Gala | D11: Silver | E11: YES | F11: 44611 | G11: 2958465 | H11: =TRUE() -> TRUE | I11: Unknown | J11: 6872343098 | K11: Pune | L11: Maharashtra | M11: India | N11: 44611
A12: 10 | B12: C0010 | C12: Wahab Raval | D12: Silver | E12: YES | F12: 44535 | G12: 2958465 | H12: =TRUE() -> TRUE | I12: wahab.raval10@example.com | J12: 9169985435 | K12: Delhi | L12: Delhi | M12: India | N12: 44535
A13: 11 | B13: C0011 | C13: Tanay Toor | D13: Silver | E13: YES | F13: 44487 | G13: 2958465 | H13: =TRUE() -> TRUE | I13: tanay.toor11@example.com | J13: 4278498084 | K13: Lucknow | L13: Uttar Pradesh | M13: India | N13: 44487
A14: 12 | B14: C0012 | C14: Aishani Tiwari | D14: Silver | E14: YES | F14: 1 | G14: 2958465 | H14: =TRUE() -> TRUE | I14: aishani.tiwari12@example.com | J14: 0052427868 | K14: Pune | L14: Maharashtra | M14: India
A15: 13 | B15: C0013 | C15: Balveer Parmar | D15: Platinum | E15: YES | F15: 44426 | G15: 2958465 | H15: =TRUE() -> TRUE | I15: balveer.parmar13@example.com | J15: 6923226025 | K15: Chennai | L15: Tamil Nadu | M15: India | N15: 44426
A16: 14 | B16: C0014 | C16: Udant Bajwa | D16: Platinum | E16: YES | F16: 44919 | G16: 2958465 | H16: =TRUE() -> TRUE | I16: udant.bajwa14@example.com | J16: 0000000000 | K16: Kolkata | L16: West Bengal | M16: India | N16: 44919
A17: 15 | B17: C0015 | C17: Chaitanya Sarin | D17: Bronze | E17: YES | F17: 44228 | G17: 2958465 | H17: =TRUE() -> TRUE | I17: chaitanya.sarin15@example.com | J17: 5951484656 | K17: Bangalore | L17: Karnataka | M17: India | N17: 44228
A18: 16 | B18: C0016 | C18: Shivansh Sani | D18: Gold | E18: YES | F18: 45204 | G18: 2958465 | H18: =TRUE() -> TRUE | I18: shivansh.sani16@example.com | J18: 3872148951 | K18: Pune | L18: Maharashtra | M18: India | N18: 45204
A19: 17 | B19: C0017 | C19: Robert Rajagopalan | D19: Platinum | E19: YES | F19: 44737 | G19: 2958465 | H19: =TRUE() -> TRUE | I19: robert.rajagopalan17@example.com | J19: 6328708317 | K19: Lucknow | L19: Uttar Pradesh | M19: India | N19: 44737
A20: 18 | B20: C0018 | C20: Aradhana Verma | D20: Gold | E20: YES | F20: 44727 | G20: 2958465 | H20: =TRUE() -> TRUE | I20: aradhana.verma18@example.com | J20: 4345581223 | K20: Mumbai | L20: Maharashtra | M20: India | N20: 44727
A21: 19 | B21: C0019 | C21: Anmol Rai | D21: Silver | E21: YES | F21: 44718 | G21: 2958465 | H21: =TRUE() -> TRUE | I21: Unknown | J21: 8893734670 | K21: Hyderabad | L21: Telangana | M21: India | N21: 44718
A22: 20 | B22: C0020 | C22: Priya Deshmukh | D22: Bronze | E22: YES | F22: 45115 | G22: 2958465 | H22: =TRUE() -> TRUE | I22: priya.deshmukh20@example.com | J22: 5375564641 | K22: Pune | L22: Maharashtra | M22: India | N22: 45115
A23: 21 | B23: C0021 | C23: William Date | D23: Silver | E23: NO | F23: 44626 | G23: 2958465 | H23: =TRUE() -> TRUE | I23: william.date21@example.com | J23: 4529912419 | K23: Delhi | L23: Delhi | M23: India | N23: 44626
A24: 22 | B24: C0022 | C24: Idika Walia | D24: Bronze | E24: YES | F24: 44665 | G24: 2958465 | H24: =TRUE() -> TRUE | I24: idika.walia22@example.com | J24: 0000000000 | K24: Bangalore | L24: Karnataka | M24: India | N24: 44665
A25: 23 | B25: C0023 | C25: Yagnesh Shetty | D25: Platinum | E25: YES | F25: 44820 | G25: 2958465 | H25: =TRUE() -> TRUE | I25: yagnesh.shetty23@example.com | J25: 5273545494 | K25: Jaipur | L25: Rajasthan | M25: India | N25: 44820
A26: 24 | B26: C0024 | C26: Nidhi Kohli | D26: Bronze | E26: YES | F26: 44208 | G26: 2958465 | H26: =TRUE() -> TRUE | I26: nidhi.kohli24@example.com | J26: 5685574443 | K26: Bengaluru | L26: Karnataka | M26: India | N26: 44208
... A160: 158 | B160: C0177 | C160: Tanay Toor | D160: Silver | E160: YES | F160: 44487 | G160: 2958465 | H160: =TRUE() -> TRUE | I160: tanay.toor11@gmail.com | J160: 4278498084 | K160: Lucknow | L160: Uttar Pradesh | M160: India | N160: 44487

Sheet DIM_SUPPLIERS
A1: supplier_key | B1: supplier_id | C1: supplier_name | D1: country | E1: is_preferred | F1: rating_raw | G1: rating_normalized | H1: contract_start_date
A2: -1 | B2: UNKNOWN | C2: Unknown supplier | D2: Unknown | E2: No
A3: 1 | B3: S001 | C3: Baral, Din And Bhalla | D3: Unknown | E3: No | F3: 4.3 | G3: 4.3 | H3: 43416
A4: 2 | B4: S002 | C4: Varughese Group | D4: Germany | E4: No | F4: 2.5 | G4: 2.5 | H4: 43499
A5: 3 | B5: S003 | C5: Bahl, Mander And Chada | D5: Vietnam | E5: No | F5: 2.9 | G5: 2.9 | H5: 44898
A6: 4 | B6: S004 | C6: Amble, Prashad And Jha | D6: Unknown | E6: Yes | F6: 9.4 | G6: 4.7 | H6: 43684
A7: 5 | B7: S005 | C7: Dhar-Gopal | D7: Germany | E7: Yes | F7: 4.5 | G7: 4.5 | H7: 43661
A8: 6 | B8: S006 | C8: Lalla, Ganesh And Oommen | D8: Germany | E8: No | F8: 7.5 | G8: 3.75 | H8: 44900
A9: 7 | B9: S007 | C9: Biswas, Karpe And Radhakrishnan | D9: Unknown | E9: No | F9: 4.2 | G9: 4.2 | H9: 45458
A10: 8 | B10: S008 | C10: Babu And Sons | D10: India | E10: No | F10: 3.7 | G10: 3.7 | H10: 44174
A11: 9 | B11: S009 | C11: Saini, Doctor And Char | D11: Germany | E11: No | F11: 4 | G11: 4 | H11: 44437
A12: 10 | B12: S010 | C12: Barad, Wali And Thakur | D12: Germany | E12: No | F12: 4.9 | G12: 4.9 | H12: 43554
A13: 11 | B13: S011 | C13: Subramaniam Ltd | D13: Vietnam | E13: No | F13: 3.3 | G13: 3.3 | H13: 45024
A14: 12 | B14: S012 | C14: Zacharia, Agarwal And Sankar | D14: Vietnam | E14: No | F14: 3 | G14: 3 | H14: 43434
... A20: 18 | B20: S018 | C20: Amble, Virk And Dalal | D20: Vietnam | E20: No | F20: 5 | G20: 5 | H20: 43114

Sheet DIM_PRODUCTS
A1: product_key | B1: product_id | C1: product_name | D1: category | E1: sub_category | F1: supplier_key | G1: unit_price | H1: cost_price | I1: is_active | J1: launch_date
A2: -1 | B2: UNKNOWN | C2: Unknown product | D2: Unknown | E2: Unknown | F2: -1
A3: 1 | B3: P001 | C3: Accessories Item 1 (Revised) | D3: Electronics | E3: Accessories | F3: 14 | G3: 10660.79 | H3: 16799.61 | I3: YES | J3: 45077
A4: 2 | B4: P002 | C4: Furniture Item 2 | D4: Home & Kitchen | E4: Furniture | F4: 7 | G4: 9953.59 | H4: 9027.17 | I4: NO | J4: 44470
A5: 3 | B5: P003 | C5: Staples Item 3 | D5: Grocery | E5: Staples | F5: 6 | H5: 10602.65 | I5: YES | J5: 44314
A6: 4 | B6: P004 | C6: Appliances Item 4 | D6: Home & Kitchen | E6: Appliances | F6: 15 | G6: 21122.18 | H6: 15898.59 | I6: YES | J6: 43828
A7: 5 | B7: P005 | C7: Staples Item 5 | D7: Grocery | E7: Staples | F7: 5 | G7: 17935.95 | H7: 14399.03 | I7: YES | J7: 44992
A8: 6 | B8: P006 | C8: Furniture Item 6 | D8: Home & Kitchen | E8: Furniture | F8: 7 | G8: 2863.09 | H8: 4549.93 | I8: YES | J8: 44060
A9: 7 | B9: P007 | C9: Outdoor Item 7 | D9: Sports | E9: Outdoor | F9: 1 | G9: 20278.89 | H9: 12749.85 | I9: YES | J9: 45469
A10: 8 | B10: P008 | C10: Unknown | D10: Fashion | E10: Menswear | F10: 13 | G10: 15176.98 | H10: 13176.38 | I10: YES | J10: 44458
A11: 9 | B11: P009 | C11: Furniture Item 9 | D11: Home & Kitchen | E11: Furniture | F11: 2 | G11: 26274.11 | H11: 19618.3 | I11: YES | J11: 44322
A12: 10 | B12: P010 | C12: Accessories Item 10 | D12: Electronics | E12: Accessories | F12: 4 | G12: 1165.83 | H12: 1730.66 | I12: YES | J12: 44111
A13: 11 | B13: P011 | C13: Beverages Item 11 | D13: Grocery | E13: Beverages | F13: 6 | G13: 1179.68 | H13: 828.75 | I13: YES | J13: 45060
A14: 12 | B14: P012 | C14: Menswear Item 12 | D14: Fashion | E14: Menswear | F14: 3 | G14: 11434.02 | H14: 8795.33 | I14: YES | J14: 45234
A15: 13 | B15: P013 | C15: Appliances Item 13 | D15: Home & Kitchen | E15: Appliances | F15: 18 | G15: 15622.68 | H15: 24940.49 | I15: YES | J15: 44434
A16: 14 | B16: P014 | C16: Audio Item 14 | D16: Electronics | E16: Audio | F16: 7 | G16: 13809.86 | H16: 10954.94 | I16: YES | J16: 45302
A17: 15 | B17: P015 | C17: Team Sports Item 15 | D17: Sports | E17: Team Sports | F17: 3 | G17: 4516.1 | H17: 3416.23 | I17: NO | J17: 44596
... A72: 70 | B72: P070 | C72: Footwear Item 70 (Revised) | D72: Fashion | E72: Footwear | F72: 8 | G72: 3962.52 | H72: 2413.18 | I72: NO | J72: 45292

Sheet DIM_DATE
A1: date_key | B1: month_name | C1: is_weekend | D1: full_date | E1: year | F1: quarter | G1: month
A2: -1 | B2: Unknown | C2: =FALSE() -> FALSE
A3: 20201029 | B3: October | C3: =FALSE() -> FALSE | D3: 44133 | E3: 2020 | F3: 4 | G3: 10
A4: 20201030 | B4: October | C4: =FALSE() -> FALSE | D4: 44134 | E4: 2020 | F4: 4 | G4: 10
A5: 20201031 | B5: October | C5: =TRUE() -> TRUE | D5: 44135 | E5: 2020 | F5: 4 | G5: 10
A6: 20201101 | B6: November | C6: =TRUE() -> TRUE | D6: 44136 | E6: 2020 | F6: 4 | G6: 11
A7: 20201102 | B7: November | C7: =FALSE() -> FALSE | D7: 44137 | E7: 2020 | F7: 4 | G7: 11
A8: 20201103 | B8: November | C8: =FALSE() -> FALSE | D8: 44138 | E8: 2020 | F8: 4 | G8: 11
A9: 20201104 | B9: November | C9: =FALSE() -> FALSE | D9: 44139 | E9: 2020 | F9: 4 | G9: 11
A10: 20201105 | B10: November | C10: =FALSE() -> FALSE | D10: 44140 | E10: 2020 | F10: 4 | G10: 11
A11: 20201106 | B11: November | C11: =FALSE() -> FALSE | D11: 44141 | E11: 2020 | F11: 4 | G11: 11
A12: 20201107 | B12: November | C12: =TRUE() -> TRUE | D12: 44142 | E12: 2020 | F12: 4 | G12: 11
A13: 20201108 | B13: November | C13: =TRUE() -> TRUE | D13: 44143 | E13: 2020 | F13: 4 | G13: 11
A14: 20201109 | B14: November | C14: =FALSE() -> FALSE | D14: 44144 | E14: 2020 | F14: 4 | G14: 11
A15: 20201110 | B15: November | C15: =FALSE() -> FALSE | D15: 44145 | E15: 2020 | F15: 4 | G15: 11
A16: 20201111 | B16: November | C16: =FALSE() -> FALSE | D16: 44146 | E16: 2020 | F16: 4 | G16: 11
A17: 20201112 | B17: November | C17: =FALSE() -> FALSE | D17: 44147 | E17: 2020 | F17: 4 | G17: 11
A18: 20201113 | B18: November | C18: =FALSE() -> FALSE | D18: 44148 | E18: 2020 | F18: 4 | G18: 11
A19: 20201114 | B19: November | C19: =TRUE() -> TRUE | D19: 44149 | E19: 2020 | F19: 4 | G19: 11
A20: 20201115 | B20: November | C20: =TRUE() -> TRUE | D20: 44150 | E20: 2020 | F20: 4 | G20: 11
A21: 20201116 | B21: November | C21: =FALSE() -> FALSE | D21: 44151 | E21: 2020 | F21: 4 | G21: 11
A22: 20201117 | B22: November | C22: =FALSE() -> FALSE | D22: 44152 | E22: 2020 | F22: 4 | G22: 11
A23: 20201118 | B23: November | C23: =FALSE() -> FALSE | D23: 44153 | E23: 2020 | F23: 4 | G23: 11
A24: 20201119 | B24: November | C24: =FALSE() -> FALSE | D24: 44154 | E24: 2020 | F24: 4 | G24: 11
A25: 20201120 | B25: November | C25: =FALSE() -> FALSE | D25: 44155 | E25: 2020 | F25: 4 | G25: 11
A26: 20201121 | B26: November | C26: =TRUE() -> TRUE | D26: 44156 | E26: 2020 | F26: 4 | G26: 11
A27: 20201122 | B27: November | C27: =TRUE() -> TRUE | D27: 44157 | E27: 2020 | F27: 4 | G27: 11
A28: 20201123 | B28: November | C28: =FALSE() -> FALSE | D28: 44158 | E28: 2020 | F28: 4 | G28: 11
A29: 20201124 | B29: November | C29: =FALSE() -> FALSE | D29: 44159 | E29: 2020 | F29: 4 | G29: 11
A30: 20201125 | B30: November | C30: =FALSE() -> FALSE | D30: 44160 | E30: 2020 | F30: 4 | G30: 11
A31: 20201126 | B31: November | C31: =FALSE() -> FALSE | D31: 44161 | E31: 2020 | F31: 4 | G31: 11
A32: 20201127 | B32: November | C32: =FALSE() -> FALSE | D32: 44162 | E32: 2020 | F32: 4 | G32: 11
A33: 20201128 | B33: November | C33: =TRUE() -> TRUE | D33: 44163 | E33: 2020 | F33: 4 | G33: 11
A34: 20201129 | B34: November | C34: =TRUE() -> TRUE | D34: 44164 | E34: 2020 | F34: 4 | G34: 11
A35: 20201130 | B35: November | C35: =FALSE() -> FALSE | D35: 44165 | E35: 2020 | F35: 4 | G35: 11
A36: 20201201 | B36: December | C36: =FALSE() -> FALSE | D36: 44166 | E36: 2020 | F36: 4 | G36: 12
A37: 20201202 | B37: December | C37: =FALSE() -> FALSE | D37: 44167 | E37: 2020 | F37: 4 | G37: 12
A38: 20201203 | B38: December | C38: =FALSE() -> FALSE | D38: 44168 | E38: 2020 | F38: 4 | G38: 12
A39: 20201204 | B39: December | C39: =FALSE() -> FALSE | D39: 44169 | E39: 2020 | F39: 4 | G39: 12
A40: 20201205 | B40: December | C40: =TRUE() -> TRUE | D40: 44170 | E40: 2020 | F40: 4 | G40: 12
A41: 20201206 | B41: December | C41: =TRUE() -> TRUE | D41: 44171 | E41: 2020 | F41: 4 | G41: 12
A42: 20201207 | B42: December | C42: =FALSE() -> FALSE | D42: 44172 | E42: 2020 | F42: 4 | G42: 12
A43: 20201208 | B43: December | C43: =FALSE() -> FALSE | D43: 44173 | E43: 2020 | F43: 4 | G43: 12
A44: 20201209 | B44: December | C44: =FALSE() -> FALSE | D44: 44174 | E44: 2020 | F44: 4 | G44: 12
A45: 20201210 | B45: December | C45: =FALSE() -> FALSE | D45: 44175 | E45: 2020 | F45: 4 | G45: 12
A46: 20201211 | B46: December | C46: =FALSE() -> FALSE | D46: 44176 | E46: 2020 | F46: 4 | G46: 12
A47: 20201212 | B47: December | C47: =TRUE() -> TRUE | D47: 44177 | E47: 2020 | F47: 4 | G47: 12
A48: 20201213 | B48: December | C48: =TRUE() -> TRUE | D48: 44178 | E48: 2020 | F48: 4 | G48: 12
A49: 20201214 | B49: December | C49: =FALSE() -> FALSE | D49: 44179 | E49: 2020 | F49: 4 | G49: 12
A50: 20201215 | B50: December | C50: =FALSE() -> FALSE | D50: 44180 | E50: 2020 | F50: 4 | G50: 12
A51: 20201216 | B51: December | C51: =FALSE() -> FALSE | D51: 44181 | E51: 2020 | F51: 4 | G51: 12
A52: 20201217 | B52: December | C52: =FALSE() -> FALSE | D52: 44182 | E52: 2020 | F52: 4 | G52: 12
A53: 20201218 | B53: December | C53: =FALSE() -> FALSE | D53: 44183 | E53: 2020 | F53: 4 | G53: 12
A54: 20201219 | B54: December | C54: =TRUE() -> TRUE | D54: 44184 | E54: 2020 | F54: 4 | G54: 12
A55: 20201220 | B55: December | C55: =TRUE() -> TRUE | D55: 44185 | E55: 2020 | F55: 4 | G55: 12
A56: 20201221 | B56: December | C56: =FALSE() -> FALSE | D56: 44186 | E56: 2020 | F56: 4 | G56: 12
A57: 20201222 | B57: December | C57: =FALSE() -> FALSE | D57: 44187 | E57: 2020 | F57: 4 | G57: 12
A58: 20201223 | B58: December | C58: =FALSE() -> FALSE | D58: 44188 | E58: 2020 | F58: 4 | G58: 12
A59: 20201224 | B59: December | C59: =FALSE() -> FALSE | D59: 44189 | E59: 2020 | F59: 4 | G59: 12
A60: 20201225 | B60: December | C60: =FALSE() -> FALSE | D60: 44190 | E60: 2020 | F60: 4 | G60: 12
A61: 20201226 | B61: December | C61: =TRUE() -> TRUE | D61: 44191 | E61: 2020 | F61: 4 | G61: 12
A62: 20201227 | B62: December | C62: =TRUE() -> TRUE | D62: 44192 | E62: 2020 | F62: 4 | G62: 12
A63: 20201228 | B63: December | C63: =FALSE() -> FALSE | D63: 44193 | E63: 2020 | F63: 4 | G63: 12
A64: 20201229 | B64: December | C64: =FALSE() -> FALSE | D64: 44194 | E64: 2020 | F64: 4 | G64: 12
A65: 20201230 | B65: December | C65: =FALSE() -> FALSE | D65: 44195 | E65: 2020 | F65: 4 | G65: 12
A66: 20201231 | B66: December | C66: =FALSE() -> FALSE | D66: 44196 | E66: 2020 | F66: 4 | G66: 12
A67: 20210101 | B67: January | C67: =FALSE() -> FALSE | D67: 44197 | E67: 2021 | F67: 1 | G67: 1
A68: 20210102 | B68: January | C68: =TRUE() -> TRUE | D68: 44198 | E68: 2021 | F68: 1 | G68: 1
A69: 20210103 | B69: January | C69: =TRUE() -> TRUE | D69: 44199 | E69: 2021 | F69: 1 | G69: 1
A70: 20210104 | B70: January | C70: =FALSE() -> FALSE | D70: 44200 | E70: 2021 | F70: 1 | G70: 1
A71: 20210105 | B71: January | C71: =FALSE() -> FALSE | D71: 44201 | E71: 2021 | F71: 1 | G71: 1
A72: 20210106 | B72: January | C72: =FALSE() -> FALSE | D72: 44202 | E72: 2021 | F72: 1 | G72: 1
A73: 20210107 | B73: January | C73: =FALSE() -> FALSE | D73: 44203 | E73: 2021 | F73: 1 | G73: 1
A74: 20210108 | B74: January | C74: =FALSE() -> FALSE | D74: 44204 | E74: 2021 | F74: 1 | G74: 1
A75: 20210109 | B75: January | C75: =TRUE() -> TRUE | D75: 44205 | E75: 2021 | F75: 1 | G75: 1
A76: 20210110 | B76: January | C76: =TRUE() -> TRUE | D76: 44206 | E76: 2021 | F76: 1 | G76: 1
A77: 20210111 | B77: January | C77: =FALSE() -> FALSE | D77: 44207 | E77: 2021 | F77: 1 | G77: 1
A78: 20210112 | B78: January | C78: =FALSE() -> FALSE | D78: 44208 | E78: 2021 | F78: 1 | G78: 1
A79: 20210113 | B79: January | C79: =FALSE() -> FALSE | D79: 44209 | E79: 2021 | F79: 1 | G79: 1
A80: 20210114 | B80: January | C80: =FALSE() -> FALSE | D80: 44210 | E80: 2021 | F80: 1 | G80: 1
A81: 20210115 | B81: January | C81: =FALSE() -> FALSE | D81: 44211 | E81: 2021 | F81: 1 | G81: 1
A82: 20210116 | B82: January | C82: =TRUE() -> TRUE | D82: 44212 | E82: 2021 | F82: 1 | G82: 1
A83: 20210117 | B83: January | C83: =TRUE() -> TRUE | D83: 44213 | E83: 2021 | F83: 1 | G83: 1
A84: 20210118 | B84: January | C84: =FALSE() -> FALSE | D84: 44214 | E84: 2021 | F84: 1 | G84: 1
A85: 20210119 | B85: January | C85: =FALSE() -> FALSE | D85: 44215 | E85: 2021 | F85: 1 | G85: 1
A86: 20210120 | B86: January | C86: =FALSE() -> FALSE | D86: 44216 | E86: 2021 | F86: 1 | G86: 1
A87: 20210121 | B87: January | C87: =FALSE() -> FALSE | D87: 44217 | E87: 2021 | F87: 1 | G87: 1
A88: 20210122 | B88: January | C88: =FALSE() -> FALSE | D88: 44218 | E88: 2021 | F88: 1 | G88: 1
A89: 20210123 | B89: January | C89: =TRUE() -> TRUE | D89: 44219 | E89: 2021 | F89: 1 | G89: 1
A90: 20210124 | B90: January | C90: =TRUE() -> TRUE | D90: 44220 | E90: 2021 | F90: 1 | G90: 1
A91: 20210125 | B91: January | C91: =FALSE() -> FALSE | D91: 44221 | E91: 2021 | F91: 1 | G91: 1
A92: 20210126 | B92: January | C92: =FALSE() -> FALSE | D92: 44222 | E92: 2021 | F92: 1 | G92: 1
A93: 20210127 | B93: January | C93: =FALSE() -> FALSE | D93: 44223 | E93: 2021 | F93: 1 | G93: 1
A94: 20210128 | B94: January | C94: =FALSE() -> FALSE | D94: 44224 | E94: 2021 | F94: 1 | G94: 1
A95: 20210129 | B95: January | C95: =FALSE() -> FALSE | D95: 44225 | E95: 2021 | F95: 1 | G95: 1
A96: 20210130 | B96: January | C96: =TRUE() -> TRUE | D96: 44226 | E96: 2021 | F96: 1 | G96: 1
A97: 20210131 | B97: January | C97: =TRUE() -> TRUE | D97: 44227 | E97: 2021 | F97: 1 | G97: 1
A98: 20210201 | B98: February | C98: =FALSE() -> FALSE | D98: 44228 | E98: 2021 | F98: 1 | G98: 2
A99: 20210202 | B99: February | C99: =FALSE() -> FALSE | D99: 44229 | E99: 2021 | F99: 1 | G99: 2
A100: 20210203 | B100: February | C100: =FALSE() -> FALSE | D100: 44230 | E100: 2021 | F100: 1 | G100: 2
...

Sheet FACT_ORDERS
A1: fact_order_key | B1: order_item_id | C1: order_id | D1: order_date_key | E1: customer_key | F1: product_key | G1: channel | H1: promo_code | I1: shipping_city | J1: order_status | K1: quantity | L1: unit_price | M1: discount_pct | N1: gross_amount | O1: discount_amount | P1: net_amount | Q1: is_returned | R1: price_imputed | S1: discount_imputed
A2: 1 | B2: OI000001 | C2: O00079 | D2: 20240129 | E2: 101 | F2: 9 | G2: App | H2: Unknown | I2: Hyderabad | J2: Completed | K2: 3 | L2: 26274.11 | M2: 5 | N2: 78822.33 | O2: 3941.12 | P2: 74881.21 | Q2: =FALSE() -> FALSE | R2: =FALSE() -> FALSE | S2: =FALSE() -> FALSE
A3: 2 | B3: OI000002 | C3: O00079 | D3: 20240129 | E3: 101 | F3: 65 | G3: App | H3: Unknown | I3: Hyderabad | J3: Completed | K3: 4 | L3: 15706.03 | M3: 20 | N3: 62824.12 | O3: 12564.82 | P3: 50259.3 | Q3: =TRUE() -> TRUE | R3: =FALSE() -> FALSE | S3: =FALSE() -> FALSE
A4: 3 | B4: OI000003 | C4: O00079 | D4: 20240129 | E4: 101 | F4: 15 | G4: App | H4: Unknown | I4: Hyderabad | J4: Completed | K4: 1 | L4: 4516.1 | M4: 5 | N4: 4516.1 | O4: 225.8 | P4: 4290.3 | Q4: =FALSE() -> FALSE | R4: =FALSE() -> FALSE | S4: =FALSE() -> FALSE
A5: 4 | B5: OI000004 | C5: O00079 | D5: 20240129 | E5: 101 | F5: 23 | G5: App | H5: Unknown | I5: Hyderabad | J5: Completed | K5: 5 | L5: 3019.36 | M5: 10 | N5: 15096.8 | O5: 1509.68 | P5: 13587.12 | Q5: =FALSE() -> FALSE | R5: =FALSE() -> FALSE | S5: =FALSE() -> FALSE
A6: 5 | B6: OI000005 | C6: O00318 | D6: 20250530 | E6: 142 | F6: 70 | G6: Store | H6: Unknown | I6: Mumbai | J6: Completed | K6: 4 | L6: 3962.52 | M6: 10 | N6: 15850.08 | O6: 1585.01 | P6: 14265.07 | Q6: =FALSE() -> FALSE | R6: =FALSE() -> FALSE | S6: =FALSE() -> FALSE
A7: 6 | B7: OI000006 | C7: O00318 | D7: 20250530 | E7: 142 | F7: 49 | G7: Store | H7: Unknown | I7: Mumbai | J7: Completed | K7: 5 | L7: 12393.99 | M7: 10 | N7: 61969.95 | O7: 6197 | P7: 55772.95 | Q7: =FALSE() -> FALSE | R7: =FALSE() -> FALSE | S7: =FALSE() -> FALSE
A8: 7 | B8: OI000007 | C8: O00130 | D8: 20240704 | E8: 139 | F8: 27 | G8: Store | H8: Unknown | I8: Chennai | J8: Pending | K8: 2 | L8: 20550.39 | M8: 0 | N8: 41100.78 | O8: 0 | P8: 41100.78 | Q8: =FALSE() -> FALSE | R8: =FALSE() -> FALSE | S8: =FALSE() -> FALSE
A9: 8 | B9: OI000008 | C9: O00130 | D9: 20240704 | E9: 139 | F9: 18 | G9: Store | H9: Unknown | I9: Chennai | J9: Pending | K9: 5 | L9: 17477.91 | M9: 10 | N9: 87389.55 | O9: 8738.96 | P9: 78650.59 | Q9: =FALSE() -> FALSE | R9: =FALSE() -> FALSE | S9: =FALSE() -> FALSE
A10: 9 | B10: OI000009 | C10: O00130 | D10: 20240704 | E10: 139 | F10: 62 | G10: Store | H10: Unknown | I10: Chennai | J10: Pending | K10: 4 | L10: 8493.72 | M10: 5 | N10: 33974.88 | O10: 1698.74 | P10: 32276.14 | Q10: =FALSE() -> FALSE | R10: =FALSE() -> FALSE | S10: =FALSE() -> FALSE
A11: 10 | B11: OI000010 | C11: O00130 | D11: 20240704 | E11: 139 | F11: 63 | G11: Store | H11: Unknown | I11: Chennai | J11: Pending | K11: 2 | L11: 9269.43 | M11: 5 | N11: 18538.86 | O11: 926.94 | P11: 17611.92 | Q11: =FALSE() -> FALSE | R11: =FALSE() -> FALSE | S11: =FALSE() -> FALSE
A12: 11 | B12: OI000011 | C12: O00137 | D12: 20250722 | E12: 60 | F12: 49 | G12: App | H12: Unknown | I12: Hyderabad | J12: Completed | K12: 5 | L12: 12393.99 | M12: 10 | N12: 61969.95 | O12: 6197 | P12: 55772.95 | Q12: =FALSE() -> FALSE | R12: =FALSE() -> FALSE | S12: =FALSE() -> FALSE
A13: 12 | B13: OI000012 | C13: O00137 | D13: 20250722 | E13: 60 | F13: 57 | G13: App | H13: Unknown | I13: Hyderabad | J13: Completed | K13: 1 | L13: 11518.86 | M13: 0 | N13: 11518.86 | O13: 0 | P13: 11518.86 | Q13: =FALSE() -> FALSE | R13: =FALSE() -> FALSE | S13: =TRUE() -> TRUE
A14: 13 | B14: OI000013 | C14: O00137 | D14: 20250722 | E14: 60 | F14: 56 | G14: App | H14: Unknown | I14: Hyderabad | J14: Completed | K14: 5 | L14: 16535.66 | M14: 20 | N14: 82678.3 | O14: 16535.66 | P14: 66142.64 | Q14: =FALSE() -> FALSE | R14: =FALSE() -> FALSE | S14: =FALSE() -> FALSE
A15: 14 | B15: OI000014 | C15: O00137 | D15: 20250722 | E15: 60 | F15: 30 | G15: App | H15: Unknown | I15: Hyderabad | J15: Completed | K15: 2 | L15: 20253.93 | M15: 10 | N15: 40507.86 | O15: 4050.79 | P15: 36457.07 | Q15: =FALSE() -> FALSE | R15: =FALSE() -> FALSE | S15: =FALSE() -> FALSE
A16: 15 | B16: OI000015 | C16: O00265 | D16: 20250508 | E16: 25 | F16: 41 | G16: App | H16: Unknown | I16: Kolkata | J16: Completed | K16: 4 | L16: 11992.92 | M16: 0 | N16: 47971.68 | O16: 0 | P16: 47971.68 | Q16: =FALSE() -> FALSE | R16: =FALSE() -> FALSE | S16: =FALSE() -> FALSE
A17: 16 | B17: OI000017 | C17: O00265 | D17: 20250508 | E17: 25 | F17: 21 | G17: App | H17: Unknown | I17: Kolkata | J17: Completed | K17: 4 | L17: 3184.81 | M17: 20 | N17: 12739.24 | O17: 2547.85 | P17: 10191.39 | Q17: =FALSE() -> FALSE | R17: =FALSE() -> FALSE | S17: =FALSE() -> FALSE
A18: 17 | B18: OI000018 | C18: O00221 | D18: 20250319 | E18: 70 | F18: 59 | G18: Store | H18: PROMO9 | I18: Bangalore | J18: Cancelled | K18: 5 | L18: 18828.5 | M18: 15 | N18: 94142.5 | O18: 14121.38 | P18: 80021.12 | Q18: =TRUE() -> TRUE | R18: =FALSE() -> FALSE | S18: =FALSE() -> FALSE
A19: 18 | B19: OI000019 | C19: O00221 | D19: 20250319 | E19: 70 | F19: 2 | G19: Store | H19: PROMO9 | I19: Bangalore | J19: Cancelled | K19: 3 | L19: 9953.59 | M19: 0 | N19: 29860.77 | O19: 0 | P19: 29860.77 | Q19: =FALSE() -> FALSE | R19: =FALSE() -> FALSE | S19: =FALSE() -> FALSE
A20: 19 | B20: OI000020 | C20: O00221 | D20: 20250319 | E20: 70 | F20: 34 | G20: Store | H20: PROMO9 | I20: Bangalore | J20: Cancelled | K20: 1 | L20: 11932.31 | M20: 0 | N20: 11932.31 | O20: 0 | P20: 11932.31 | Q20: =FALSE() -> FALSE | R20: =FALSE() -> FALSE | S20: =FALSE() -> FALSE
A21: 20 | B21: OI000021 | C21: O00247 | D21: 20250629 | E21: -1 | F21: 62 | G21: App | H21: PROMO14 | I21: Chennai | J21: Pending | K21: 1 | L21: 8493.72 | M21: 0 | N21: 8493.72 | O21: 0 | P21: 8493.72 | Q21: =FALSE() -> FALSE | R21: =FALSE() -> FALSE | S21: =FALSE() -> FALSE
A22: 21 | B22: OI000022 | C22: O00247 | D22: 20250629 | E22: -1 | F22: 32 | G22: App | H22: PROMO14 | I22: Chennai | J22: Pending | K22: 4 | L22: 23243.35 | M22: 20 | N22: 92973.4 | O22: 18594.68 | P22: 74378.72 | Q22: =FALSE() -> FALSE | R22: =FALSE() -> FALSE | S22: =FALSE() -> FALSE
A23: 22 | B23: OI000023 | C23: O00247 | D23: 20250629 | E23: -1 | F23: 51 | G23: App | H23: PROMO14 | I23: Chennai | J23: Pending | K23: 4 | L23: 2089.56 | M23: 15 | N23: 8358.24 | O23: 1253.74 | P23: 7104.5 | Q23: =FALSE() -> FALSE | R23: =FALSE() -> FALSE | S23: =FALSE() -> FALSE
A24: 23 | B24: OI000024 | C24: O00077 | D24: 20250526 | E24: 3 | F24: 50 | G24: Store | H24: PROMO9 | I24: Jaipur | J24: Pending | K24: 2 | L24: 22582.54 | M24: 15 | N24: 45165.08 | O24: 6774.76 | P24: 38390.32 | Q24: =FALSE() -> FALSE | R24: =FALSE() -> FALSE | S24: =FALSE() -> FALSE
A25: 24 | B25: OI000025 | C25: O00077 | D25: 20250526 | E25: 3 | F25: 41 | G25: Store | H25: PROMO9 | I25: Jaipur | J25: Pending | K25: 3 | L25: 11992.92 | M25: 10 | N25: 35978.76 | O25: 3597.88 | P25: 32380.88 | Q25: =FALSE() -> FALSE | R25: =FALSE() -> FALSE | S25: =FALSE() -> FALSE
A26: 25 | B26: OI000026 | C26: O00126 | D26: 20240629 | E26: 29 | F26: 28 | G26: App | H26: PROMO15 | I26: Pune | J26: Completed | K26: 2 | L26: 7218.53 | M26: 0 | N26: 14437.06 | O26: 0 | P26: 14437.06 | Q26: =FALSE() -> FALSE | R26: =FALSE() -> FALSE | S26: =FALSE() -> FALSE
A27: 26 | B27: OI000027 | C27: O00126 | D27: 20240629 | E27: 29 | F27: 42 | G27: App | H27: PROMO15 | I27: Pune | J27: Completed | K27: 1 | L27: 11284.39 | M27: 0 | N27: 11284.39 | O27: 0 | P27: 11284.39 | Q27: =TRUE() -> TRUE | R27: =FALSE() -> FALSE | S27: =FALSE() -> FALSE
A28: 27 | B28: OI000028 | C28: O00230 | D28: 20251104 | E28: 70 | F28: 32 | G28: Web | H28: Unknown | I28: Bangalore | J28: Pending | K28: 2 | L28: 23243.35 | M28: 0 | N28: 46486.7 | O28: 0 | P28: 46486.7 | Q28: =FALSE() -> FALSE | R28: =FALSE() -> FALSE | S28: =FALSE() -> FALSE
A29: 28 | B29: OI000029 | C29: O00230 | D29: 20251104 | E29: 70 | F29: 54 | G29: Web | H29: Unknown | I29: Bangalore | J29: Pending | K29: 4 | L29: 20481.04 | M29: 10 | N29: 81924.16 | O29: 8192.42 | P29: 73731.74 | Q29: =FALSE() -> FALSE | R29: =FALSE() -> FALSE | S29: =FALSE() -> FALSE
A30: 29 | B30: OI000030 | C30: O00230 | D30: 20251104 | E30: 70 | F30: 37 | G30: Web | H30: Unknown | I30: Bangalore | J30: Pending | K30: 4 | L30: 16084.14 | M30: 15 | N30: 64336.56 | O30: 9650.48 | P30: 54686.08 | Q30: =FALSE() -> FALSE | R30: =FALSE() -> FALSE | S30: =FALSE() -> FALSE
A31: 30 | B31: OI000031 | C31: O00230 | D31: 20251104 | E31: 70 | F31: 37 | G31: Web | H31: Unknown | I31: Bangalore | J31: Pending | K31: 4 | L31: 16084.14 | M31: 10 | N31: 64336.56 | O31: 6433.66 | P31: 57902.9 | Q31: =FALSE() -> FALSE | R31: =FALSE() -> FALSE | S31: =FALSE() -> FALSE
A32: 31 | B32: OI000032 | C32: O00272 | D32: 20250831 | E32: 121 | F32: 10 | G32: Store | H32: Unknown | I32: Lucknow | J32: Cancelled | K32: 5 | L32: 1165.83 | M32: 0 | N32: 5829.15 | O32: 0 | P32: 5829.15 | Q32: =FALSE() -> FALSE | R32: =FALSE() -> FALSE | S32: =FALSE() -> FALSE
A33: 32 | B33: OI000033 | C33: O00272 | D33: 20250831 | E33: 121 | F33: 7 | G33: Store | H33: Unknown | I33: Lucknow | J33: Cancelled | K33: 2 | L33: 20278.89 | M33: 20 | N33: 40557.78 | O33: 8111.56 | P33: 32446.22 | Q33: =FALSE() -> FALSE | R33: =FALSE() -> FALSE | S33: =FALSE() -> FALSE
A34: 33 | B34: OI000034 | C34: O00272 | D34: 20250831 | E34: 121 | F34: 64 | G34: Store | H34: Unknown | I34: Lucknow | J34: Cancelled | K34: 5 | L34: 11089.19 | M34: 15 | N34: 55445.95 | O34: 8316.89 | P34: 47129.06 | Q34: =FALSE() -> FALSE | R34: =FALSE() -> FALSE | S34: =FALSE() -> FALSE
A35: 34 | B35: OI000035 | C35: O00254 | D35: 20241115 | E35: 88 | F35: -1 | G35: Store | H35: Unknown | I35: Kolkata | J35: Completed | K35: 5 | L35: 5818.64 | M35: 10 | N35: 29093.2 | O35: 2909.32 | P35: 26183.88 | Q35: =FALSE() -> FALSE | R35: =FALSE() -> FALSE | S35: =FALSE() -> FALSE
A36: 35 | B36: OI000036 | C36: O00254 | D36: 20241115 | E36: 88 | F36: 34 | G36: Store | H36: Unknown | I36: Kolkata | J36: Completed | K36: 4 | L36: 11932.31 | M36: 20 | N36: 47729.24 | O36: 9545.85 | P36: 38183.39 | Q36: =TRUE() -> TRUE | R36: =FALSE() -> FALSE | S36: =FALSE() -> FALSE
A37: 36 | B37: OI000037 | C37: O00254 | D37: 20241115 | E37: 88 | F37: 29 | G37: Store | H37: Unknown | I37: Kolkata | J37: Completed | K37: 5 | L37: 7855.79 | M37: 5 | N37: 39278.95 | O37: 1963.95 | P37: 37315 | Q37: =FALSE() -> FALSE | R37: =FALSE() -> FALSE | S37: =FALSE() -> FALSE
A38: 37 | B38: OI000038 | C38: O00110 | D38: 20250101 | E38: 95 | F38: 11 | G38: Web | H38: PROMO16 | I38: Chennai | J38: Completed | K38: 5 | L38: 1179.68 | M38: 0 | N38: 5898.4 | O38: 0 | P38: 5898.4 | Q38: =FALSE() -> FALSE | R38: =FALSE() -> FALSE | S38: =FALSE() -> FALSE
A39: 38 | B39: OI000039 | C39: O00110 | D39: 20250101 | E39: 95 | F39: 70 | G39: Web | H39: PROMO16 | I39: Chennai | J39: Completed | K39: 1 | L39: 3962.52 | M39: 20 | N39: 3962.52 | O39: 792.5 | P39: 3170.02 | Q39: =FALSE() -> FALSE | R39: =FALSE() -> FALSE | S39: =FALSE() -> FALSE
A40: 39 | B40: OI000040 | C40: O00110 | D40: 20250101 | E40: 95 | F40: 67 | G40: Web | H40: PROMO16 | I40: Chennai | J40: Completed | K40: 3 | L40: 14595.44 | M40: 15 | N40: 43786.32 | O40: 6567.95 | P40: 37218.37 | Q40: =FALSE() -> FALSE | R40: =FALSE() -> FALSE | S40: =FALSE() -> FALSE
A41: 40 | B41: OI000041 | C41: O00110 | D41: 20250101 | E41: 95 | F41: 58 | G41: Web | H41: PROMO16 | I41: Chennai | J41: Completed | K41: 5 | L41: 22572.25 | M41: 0 | N41: 112861.25 | O41: 0 | P41: 112861.25 | Q41: =FALSE() -> FALSE | R41: =FALSE() -> FALSE | S41: =FALSE() -> FALSE
A42: 41 | B42: OI000042 | C42: O00174 | D42: 20240422 | E42: 98 | F42: 55 | G42: Web | H42: Unknown | I42: Lucknow | J42: Returned | K42: 4 | L42: 5471.28 | M42: 15 | N42: 21885.12 | O42: 3282.77 | P42: 18602.35 | Q42: =FALSE() -> FALSE | R42: =FALSE() -> FALSE | S42: =FALSE() -> FALSE
A43: 42 | B43: OI000043 | C43: O00174 | D43: 20240422 | E43: 98 | F43: 16 | G43: Web | H43: Unknown | I43: Lucknow | J43: Returned | K43: 3 | L43: 2260.53 | M43: 5 | N43: 6781.59 | O43: 339.08 | P43: 6442.51 | Q43: =FALSE() -> FALSE | R43: =FALSE() -> FALSE | S43: =FALSE() -> FALSE
A44: 43 | B44: OI000044 | C44: O00174 | D44: 20240422 | E44: 98 | F44: 12 | G44: Web | H44: Unknown | I44: Lucknow | J44: Returned | K44: 5 | L44: 11434.02 | M44: 20 | N44: 57170.1 | O44: 11434.02 | P44: 45736.08 | Q44: =FALSE() -> FALSE | R44: =FALSE() -> FALSE | S44: =FALSE() -> FALSE
A45: 44 | B45: OI000045 | C45: O00174 | D45: 20240422 | E45: 98 | F45: 21 | G45: Web | H45: Unknown | I45: Lucknow | J45: Returned | K45: 5 | L45: 3184.81 | M45: 5 | N45: 15924.05 | O45: 796.2 | P45: 15127.85 | Q45: =TRUE() -> TRUE | R45: =FALSE() -> FALSE | S45: =FALSE() -> FALSE
A46: 45 | B46: OI000046 | C46: O00157 | D46: 20240322 | E46: 31 | F46: 68 | G46: Store | H46: Unknown | I46: Kolkata | J46: Completed | K46: 5 | L46: 21978.46 | M46: 0 | N46: 109892.3 | O46: 0 | P46: 109892.3 | Q46: =FALSE() -> FALSE | R46: =FALSE() -> FALSE | S46: =FALSE() -> FALSE
A47: 46 | B47: OI000047 | C47: O00103 | D47: 20250604 | E47: 20 | F47: 6 | G47: App | H47: Unknown | I47: Pune | J47: Completed | K47: 1 | L47: 2863.09 | M47: 0 | N47: 2863.09 | O47: 0 | P47: 2863.09 | Q47: =FALSE() -> FALSE | R47: =FALSE() -> FALSE | S47: =FALSE() -> FALSE
A48: 47 | B48: OI000048 | C48: O00103 | D48: 20250604 | E48: 20 | F48: 64 | G48: App | H48: Unknown | I48: Pune | J48: Completed | K48: 3 | L48: 11089.19 | M48: 5 | N48: 33267.57 | O48: 1663.38 | P48: 31604.19 | Q48: =FALSE() -> FALSE | R48: =FALSE() -> FALSE | S48: =FALSE() -> FALSE
A49: 48 | B49: OI000049 | C49: O00103 | D49: 20250604 | E49: 20 | F49: 65 | G49: App | H49: Unknown | I49: Pune | J49: Completed | K49: 3 | L49: 15706.03 | M49: 5 | N49: 47118.09 | O49: 2355.9 | P49: 44762.19 | Q49: =FALSE() -> FALSE | R49: =FALSE() -> FALSE | S49: =FALSE() -> FALSE
A50: 49 | B50: OI000050 | C50: O00191 | D50: 20250127 | E50: 123 | F50: 62 | G50: Web | H50: Unknown | I50: Hyderabad | J50: Cancelled | K50: 5 | L50: 8493.72 | M50: 20 | N50: 42468.6 | O50: 8493.72 | P50: 33974.88 | Q50: =FALSE() -> FALSE | R50: =FALSE() -> FALSE | S50: =FALSE() -> FALSE
A51: 50 | B51: OI000051 | C51: O00022 | D51: 20240715 | E51: 5 | F51: 40 | G51: Store | H51: Unknown | I51: Pune | J51: Cancelled | K51: 2 | L51: 959.46 | M51: 10 | N51: 1918.92 | O51: 191.89 | P51: 1727.03 | Q51: =FALSE() -> FALSE | R51: =FALSE() -> FALSE | S51: =FALSE() -> FALSE
A52: 51 | B52: OI000052 | C52: O00022 | D52: 20240715 | E52: 5 | F52: 1 | G52: Store | H52: Unknown | I52: Pune | J52: Cancelled | K52: 1 | L52: 10660.79 | M52: 5 | N52: 10660.79 | O52: 533.04 | P52: 10127.75 | Q52: =FALSE() -> FALSE | R52: =FALSE() -> FALSE | S52: =FALSE() -> FALSE
A53: 52 | B53: OI000053 | C53: O00270 | D53: 20240609 | E53: 83 | F53: 69 | G53: App | H53: PROMO14 | I53: Chennai | J53: Cancelled | K53: 2 | L53: 25742.49 | M53: 10 | N53: 51484.98 | O53: 5148.5 | P53: 46336.48 | Q53: =FALSE() -> FALSE | R53: =FALSE() -> FALSE | S53: =FALSE() -> FALSE
A54: 53 | B54: OI000054 | C54: O00118 | D54: 20240609 | E54: 77 | F54: 41 | G54: App | H54: Unknown | I54: Lucknow | J54: Returned | K54: 4 | L54: 11992.92 | M54: 20 | N54: 47971.68 | O54: 9594.34 | P54: 38377.34 | Q54: =FALSE() -> FALSE | R54: =FALSE() -> FALSE | S54: =FALSE() -> FALSE
A55: 54 | B55: OI000055 | C55: O00118 | D55: 20240609 | E55: 77 | F55: 12 | G55: App | H55: Unknown | I55: Lucknow | J55: Returned | K55: 3 | L55: 11434.02 | M55: 0 | N55: 34302.06 | O55: 0 | P55: 34302.06 | Q55: =FALSE() -> FALSE | R55: =FALSE() -> FALSE | S55: =FALSE() -> FALSE
A56: 55 | B56: OI000056 | C56: O00118 | D56: 20240609 | E56: 77 | F56: 17 | G56: App | H56: Unknown | I56: Lucknow | J56: Returned | K56: 1 | L56: 17485.19 | M56: 0 | N56: 17485.19 | O56: 0 | P56: 17485.19 | Q56: =FALSE() -> FALSE | R56: =FALSE() -> FALSE | S56: =FALSE() -> FALSE
A57: 56 | B57: OI000057 | C57: O00118 | D57: 20240609 | E57: 77 | F57: 12 | G57: App | H57: Unknown | I57: Lucknow | J57: Returned | K57: 4 | L57: 11434.02 | M57: 5 | N57: 45736.08 | O57: 2286.8 | P57: 43449.28 | Q57: =FALSE() -> FALSE | R57: =FALSE() -> FALSE | S57: =FALSE() -> FALSE
... A82: 81 | B82: OI000083 | C82: O00102 | D82: 20240311 | E82: -1 | F82: 8 | G82: App | H82: PROMO15 | I82: Lucknow | J82: Completed | K82: 3 | L82: 15176.98 | M82: 10 | N82: 45530.94 | O82: 4553.09 | P82: 40977.85 | Q82: =FALSE() -> FALSE | R82: =FALSE() -> FALSE | S82: =FALSE() -> FALSE
A83: 82 | B83: OI000084 | C83: O00102 | D83: 20240311 | E83: -1 | F83: 30 | G83: App | H83: PROMO15 | I83: Lucknow | J83: Completed | K83: 4 | L83: 20253.93 | M83: 10 | N83: 81015.72 | O83: 8101.57 | P83: 72914.15 | Q83: =TRUE() -> TRUE | R83: =FALSE() -> FALSE | S83: =FALSE() -> FALSE
A84: 83 | B84: OI000085 | C84: O00102 | D84: 20240311 | E84: -1 | F84: 32 | G84: App | H84: PROMO15 | I84: Lucknow | J84: Completed | K84: 1 | L84: 23243.35 | M84: 15 | N84: 23243.35 | O84: 3486.5 | P84: 19756.85 | Q84: =FALSE() -> FALSE | R84: =FALSE() -> FALSE | S84: =FALSE() -> FALSE
A85: 84 | B85: OI000086 | C85: O00102 | D85: 20240311 | E85: -1 | F85: 10 | G85: App | H85: PROMO15 | I85: Lucknow | J85: Completed | K85: 4 | L85: 1165.83 | M85: 0 | N85: 4663.32 | O85: 0 | P85: 4663.32 | Q85: =FALSE() -> FALSE | R85: =FALSE() -> FALSE | S85: =FALSE() -> FALSE
A86: 85 | B86: OI000087 | C86: O00127 | D86: 20240606 | E86: -1 | F86: 16 | G86: Store | H86: Unknown | I86: Delhi | J86: Completed | K86: 4 | L86: 2260.53 | M86: 0 | N86: 9042.12 | O86: 0 | P86: 9042.12 | Q86: =FALSE() -> FALSE | R86: =FALSE() -> FALSE | S86: =FALSE() -> FALSE
A87: 86 | B87: OI000088 | C87: O00127 | D87: 20240606 | E87: -1 | F87: 59 | G87: Store | H87: Unknown | I87: Delhi | J87: Completed | K87: 3 | L87: 18828.5 | M87: 0 | N87: 56485.5 | O87: 0 | P87: 56485.5 | Q87: =FALSE() -> FALSE | R87: =FALSE() -> FALSE | S87: =FALSE() -> FALSE
A88: 87 | B88: OI000089 | C88: O00127 | D88: 20240606 | E88: -1 | F88: 55 | G88: Store | H88: Unknown | I88: Delhi | J88: Completed | K88: 3 | L88: 5471.28 | M88: 20 | N88: 16413.84 | O88: 3282.77 | P88: 13131.07 | Q88: =FALSE() -> FALSE | R88: =FALSE() -> FALSE | S88: =FALSE() -> FALSE
A89: 88 | B89: OI000090 | C89: O00075 | D89: 20250319 | E89: 29 | F89: 50 | G89: App | H89: Unknown | I89: Chennai | J89: Returned | K89: 4 | L89: 22582.54 | M89: 20 | N89: 90330.16 | O89: 18066.03 | P89: 72264.13 | Q89: =FALSE() -> FALSE | R89: =FALSE() -> FALSE | S89: =FALSE() -> FALSE
A90: 89 | B90: OI000091 | C90: O00075 | D90: 20250319 | E90: 29 | F90: 61 | G90: App | H90: Unknown | I90: Chennai | J90: Returned | K90: 4 | L90: 8318.56 | M90: 0 | N90: 33274.24 | O90: 0 | P90: 33274.24 | Q90: =FALSE() -> FALSE | R90: =FALSE() -> FALSE | S90: =FALSE() -> FALSE
A91: 90 | B91: OI000093 | C91: O00104 | D91: 20240108 | E91: 117 | F91: 61 | G91: Store | H91: PROMO18 | I91: Ahmedabad | J91: Completed | K91: 2 | L91: 8318.56 | M91: 0 | N91: 16637.12 | O91: 0 | P91: 16637.12 | Q91: =FALSE() -> FALSE | R91: =FALSE() -> FALSE | S91: =FALSE() -> FALSE
A92: 91 | B92: OI000094 | C92: O00104 | D92: 20240108 | E92: 117 | F92: 48 | G92: Store | H92: PROMO18 | I92: Ahmedabad | J92: Completed | K92: 1 | L92: 25643.17 | M92: 15 | N92: 25643.17 | O92: 3846.48 | P92: 21796.69 | Q92: =FALSE() -> FALSE | R92: =FALSE() -> FALSE | S92: =FALSE() -> FALSE
A93: 92 | B93: OI000095 | C93: O00279 | D93: 20250724 | E93: 54 | F93: 7 | G93: Store | H93: Unknown | I93: Lucknow | J93: Returned | K93: 4 | L93: 20278.89 | M93: 0 | N93: 81115.56 | O93: 0 | P93: 81115.56 | Q93: =FALSE() -> FALSE | R93: =FALSE() -> FALSE | S93: =FALSE() -> FALSE
A94: 93 | B94: OI000096 | C94: O00279 | D94: 20250724 | E94: 54 | F94: 39 | G94: Store | H94: Unknown | I94: Lucknow | J94: Returned | K94: 3 | L94: 5818.64 | M94: 20 | N94: 17455.92 | O94: 3491.18 | P94: 13964.74 | Q94: =FALSE() -> FALSE | R94: =FALSE() -> FALSE | S94: =FALSE() -> FALSE
A95: 94 | B95: OI000097 | C95: O00279 | D95: 20250724 | E95: 54 | F95: 5 | G95: Store | H95: Unknown | I95: Lucknow | J95: Returned | K95: 2 | L95: 17935.95 | M95: 20 | N95: 35871.9 | O95: 7174.38 | P95: 28697.52 | Q95: =FALSE() -> FALSE | R95: =FALSE() -> FALSE | S95: =FALSE() -> FALSE
... A113: 112 | B113: OI000116 | C113: O00083 | D113: 20251021 | E113: 77 | F113: 1 | G113: Web | H113: PROMO4 | I113: Pune | J113: Completed | K113: 5 | L113: 10660.79 | M113: 0 | N113: 53303.95 | O113: 0 | P113: 53303.95 | Q113: =FALSE() -> FALSE | R113: =FALSE() -> FALSE | S113: =FALSE() -> FALSE
A114: 113 | B114: OI000117 | C114: O00294 | D114: 20250501 | E114: 5 | F114: 52 | G114: Web | H114: Unknown | I114: Mumbai | J114: Completed | K114: 5 | L114: 17637.28 | M114: 0 | N114: 88186.4 | O114: 0 | P114: 88186.4 | Q114: =TRUE() -> TRUE | R114: =FALSE() -> FALSE | S114: =FALSE() -> FALSE
A115: 114 | B115: OI000118 | C115: O00294 | D115: 20250501 | E115: 5 | F115: 61 | G115: Web | H115: Unknown | I115: Mumbai | J115: Completed | K115: 5 | L115: 8318.56 | M115: 0 | N115: 41592.8 | O115: 0 | P115: 41592.8 | Q115: =FALSE() -> FALSE | R115: =FALSE() -> FALSE | S115: =FALSE() -> FALSE
A116: 115 | B116: OI000119 | C116: O00294 | D116: 20250501 | E116: 5 | F116: 31 | G116: Web | H116: Unknown | I116: Mumbai | J116: Completed | K116: 5 | L116: 20098.63 | M116: 15 | N116: 100493.15 | O116: 15073.97 | P116: 85419.18 | Q116: =FALSE() -> FALSE | R116: =FALSE() -> FALSE | S116: =FALSE() -> FALSE
A117: 116 | B117: OI000120 | C117: O00041 | D117: 20250227 | E117: 32 | F117: 9 | G117: Web | H117: PROMO4 | I117: Delhi | J117: Completed | K117: 2 | L117: 26274.11 | M117: 0 | N117: 52548.22 | O117: 0 | P117: 52548.22 | Q117: =FALSE() -> FALSE | R117: =FALSE() -> FALSE | S117: =TRUE() -> TRUE
A118: 117 | B118: OI000121 | C118: O00041 | D118: 20250227 | E118: 32 | F118: 58 | G118: Web | H118: PROMO4 | I118: Delhi | J118: Completed | K118: 2 | L118: 22572.25 | M118: 20 | N118: 45144.5 | O118: 9028.9 | P118: 36115.6 | Q118: =FALSE() -> FALSE | R118: =FALSE() -> FALSE | S118: =FALSE() -> FALSE
A119: 118 | B119: OI000122 | C119: O00091 | D119: 20250120 | E119: 2 | F119: -1 | G119: Store | H119: Unknown | I119: Lucknow | J119: Returned | K119: 1 | L119: 20278.89 | M119: 0 | N119: 20278.89 | O119: 0 | P119: 20278.89 | Q119: =FALSE() -> FALSE | R119: =FALSE() -> FALSE | S119: =FALSE() -> FALSE
A120: 119 | B120: OI000123 | C120: O00091 | D120: 20250120 | E120: 2 | F120: 31 | G120: Store | H120: Unknown | I120: Lucknow | J120: Returned | K120: 4 | L120: 20098.63 | M120: 0 | N120: 80394.52 | O120: 0 | P120: 80394.52 | Q120: =FALSE() -> FALSE | R120: =FALSE() -> FALSE | S120: =TRUE() -> TRUE
A121: 120 | B121: OI000124 | C121: O00091 | D121: 20250120 | E121: 2 | F121: 16 | G121: Store | H121: Unknown | I121: Lucknow | J121: Returned | K121: 4 | L121: 2260.53 | M121: 0 | N121: 9042.12 | O121: 0 | P121: 9042.12 | Q121: =FALSE() -> FALSE | R121: =FALSE() -> FALSE | S121: =FALSE() -> FALSE
A122: 121 | B122: OI000125 | C122: O00091 | D122: 20250120 | E122: 2 | F122: 15 | G122: Store | H122: Unknown | I122: Lucknow | J122: Returned | K122: 5 | L122: 4516.1 | M122: 15 | N122: 22580.5 | O122: 3387.08 | P122: 19193.42 | Q122: =FALSE() -> FALSE | R122: =FALSE() -> FALSE | S122: =FALSE() -> FALSE
A123: 122 | B123: OI000126 | C123: O00296 | D123: 20240410 | E123: 111 | F123: 6 | G123: Web | H123: Unknown | I123: Pune | J123: Cancelled | K123: 1 | L123: 2863.09 | M123: 0 | N123: 2863.09 | O123: 0 | P123: 2863.09 | Q123: =FALSE() -> FALSE | R123: =FALSE() -> FALSE | S123: =FALSE() -> FALSE
A124: 123 | B124: OI000127 | C124: O00296 | D124: 20240410 | E124: 111 | F124: 48 | G124: Web | H124: Unknown | I124: Pune | J124: Cancelled | K124: 5 | L124: 25643.17 | M124: 15 | N124: 128215.85 | O124: 19232.38 | P124: 108983.47 | Q124: =FALSE() -> FALSE | R124: =FALSE() -> FALSE | S124: =FALSE() -> FALSE
A125: 124 | B125: OI000128 | C125: O00285 | D125: 20250220 | E125: 35 | F125: 53 | G125: Web | H125: PROMO10 | I125: Ahmedabad | J125: Completed | K125: 3 | L125: 7313.65 | M125: 0 | N125: 21940.95 | O125: 0 | P125: 21940.95 | Q125: =FALSE() -> FALSE | R125: =TRUE() -> TRUE | S125: =FALSE() -> FALSE
A126: 125 | B126: OI000129 | C126: O00285 | D126: 20250220 | E126: 35 | F126: 62 | G126: Web | H126: PROMO10 | I126: Ahmedabad | J126: Completed | K126: 1 | L126: 8493.72 | M126: 0 | N126: 8493.72 | O126: 0 | P126: 8493.72 | Q126: =FALSE() -> FALSE | R126: =FALSE() -> FALSE | S126: =FALSE() -> FALSE
A127: 126 | B127: OI000130 | C127: O00285 | D127: 20250220 | E127: 35 | F127: 35 | G127: Web | H127: PROMO10 | I127: Ahmedabad | J127: Completed | K127: 4 | L127: 1741.05 | M127: 0 | N127: 6964.2 | O127: 0 | P127: 6964.2 | Q127: =FALSE() -> FALSE | R127: =FALSE() -> FALSE | S127: =FALSE() -> FALSE
A128: 127 | B128: OI000131 | C128: O00158 | D128: 20250308 | E128: 124 | F128: 68 | G128: App | H128: Unknown | I128: Mumbai | J128: Completed | K128: 1 | L128: 21978.46 | M128: 10 | N128: 21978.46 | O128: 2197.85 | P128: 19780.61 | Q128: =FALSE() -> FALSE | R128: =FALSE() -> FALSE | S128: =FALSE() -> FALSE
A129: 128 | B129: OI000132 | C129: O00295 | D129: 20240604 | E129: 71 | F129: 56 | G129: Web | H129: Unknown | I129: Mumbai | J129: Pending | K129: 4 | L129: 16535.66 | M129: 0 | N129: 66142.64 | O129: 0 | P129: 66142.64 | Q129: =FALSE() -> FALSE | R129: =FALSE() -> FALSE | S129: =FALSE() -> FALSE
A130: 129 | B130: OI000133 | C130: O00295 | D130: 20240604 | E130: 71 | F130: 41 | G130: Web | H130: Unknown | I130: Mumbai | J130: Pending | K130: 4 | L130: 11992.92 | M130: 20 | N130: 47971.68 | O130: 9594.34 | P130: 38377.34 | Q130: =FALSE() -> FALSE | R130: =FALSE() -> FALSE | S130: =FALSE() -> FALSE
A131: 130 | B131: OI000134 | C131: O00029 | D131: 20250409 | E131: 59 | F131: 43 | G131: Web | H131: PROMO10 | I131: Jaipur | J131: Cancelled | K131: 2 | L131: 4511.74 | M131: 5 | N131: 9023.48 | O131: 451.17 | P131: 8572.31 | Q131: =FALSE() -> FALSE | R131: =FALSE() -> FALSE | S131: =FALSE() -> FALSE
A132: 131 | B132: OI000135 | C132: O00029 | D132: 20250409 | E132: 59 | F132: 65 | G132: Web | H132: PROMO10 | I132: Jaipur | J132: Cancelled | K132: 5 | L132: 15706.03 | M132: 0 | N132: 78530.15 | O132: 0 | P132: 78530.15 | Q132: =FALSE() -> FALSE | R132: =FALSE() -> FALSE | S132: =FALSE() -> FALSE
A133: 132 | B133: OI000136 | C133: O00309 | D133: 20240217 | E133: 77 | F133: 54 | G133: App | H133: Unknown | I133: Lucknow | J133: Pending | K133: 4 | L133: 20481.04 | M133: 10 | N133: 81924.16 | O133: 8192.42 | P133: 73731.74 | Q133: =FALSE() -> FALSE | R133: =FALSE() -> FALSE | S133: =FALSE() -> FALSE
A134: 133 | B134: OI000137 | C134: O00309 | D134: 20240217 | E134: 77 | F134: 53 | G134: App | H134: Unknown | I134: Lucknow | J134: Pending | K134: 3 | L134: 7313.65 | M134: 0 | N134: 21940.95 | O134: 0 | P134: 21940.95 | Q134: =FALSE() -> FALSE | R134: =FALSE() -> FALSE | S134: =FALSE() -> FALSE
A135: 134 | B135: OI000138 | C135: O00309 | D135: 20240217 | E135: 77 | F135: 46 | G135: App | H135: Unknown | I135: Lucknow | J135: Pending | K135: 5 | L135: 15383.27 | M135: 0 | N135: 76916.35 | O135: 0 | P135: 76916.35 | Q135: =FALSE() -> FALSE | R135: =FALSE() -> FALSE | S135: =FALSE() -> FALSE
A136: 135 | B136: OI000139 | C136: O00212 | D136: 20250314 | E136: 157 | F136: 59 | G136: App | H136: Unknown | I136: Delhi | J136: Completed | K136: 5 | L136: 18828.5 | M136: 10 | N136: 94142.5 | O136: 9414.25 | P136: 84728.25 | Q136: =FALSE() -> FALSE | R136: =FALSE() -> FALSE | S136: =FALSE() -> FALSE
A137: 136 | B137: OI000140 | C137: O00212 | D137: 20250314 | E137: 157 | F137: 56 | G137: App | H137: Unknown | I137: Delhi | J137: Completed | K137: 4 | L137: 16535.66 | M137: 5 | N137: 66142.64 | O137: 3307.13 | P137: 62835.51 | Q137: =FALSE() -> FALSE | R137: =FALSE() -> FALSE | S137: =FALSE() -> FALSE
... A150: 149 | B150: OI000154 | C150: O00074 | D150: 20250328 | E150: 117 | F150: 46 | G150: Store | H150: PROMO17 | I150: Hyderabad | J150: Completed | K150: 3 | L150: 15383.27 | M150: 20 | N150: 46149.81 | O150: 9229.96 | P150: 36919.85 | Q150: =FALSE() -> FALSE | R150: =FALSE() -> FALSE | S150: =FALSE() -> FALSE
A151: 150 | B151: OI000155 | C151: O00119 | D151: 20250725 | E151: 19 | F151: 29 | G151: Web | H151: Unknown | I151: Bangalore | J151: Completed | K151: 3 | L151: 7855.79 | M151: 20 | N151: 23567.37 | O151: 4713.47 | P151: 18853.9 | Q151: =TRUE() -> TRUE | R151: =FALSE() -> FALSE | S151: =FALSE() -> FALSE
A152: 151 | B152: OI000156 | C152: O00119 | D152: 20250725 | E152: 19 | F152: 33 | G152: Web | H152: Unknown | I152: Bangalore | J152: Completed | K152: 3 | L152: 11865.75 | M152: 0 | N152: 35597.25 | O152: 0 | P152: 35597.25 | Q152: =FALSE() -> FALSE | R152: =FALSE() -> FALSE | S152: =FALSE() -> FALSE
A153: 152 | B153: OI000157 | C153: O00218 | D153: 20240328 | E153: 136 | F153: 41 | G153: App | H153: Unknown | I153: Hyderabad | J153: Returned | K153: 5 | L153: 11992.92 | M153: 0 | N153: 59964.6 | O153: 0 | P153: 59964.6 | Q153: =FALSE() -> FALSE | R153: =FALSE() -> FALSE | S153: =FALSE() -> FALSE
...

Sheet FACT_PAYMENTS
A1: fact_payment_key | B1: payment_id | C1: order_id | D1: payment_date_key | E1: customer_key | F1: payment_method | G1: payment_status | H1: amount_paid | I1: is_orphan_order
A2: 1 | B2: PM00001 | C2: O00079 | D2: 20240123 | E2: 101 | F2: Credit Card | G2: Refunded | H2: 217899.14 | I2: =FALSE() -> FALSE
A3: 2 | B3: PM00002 | C3: O00318 | D3: 20240411 | E3: 142 | F3: Netbanking | G3: Success | H3: 70038.03 | I3: =FALSE() -> FALSE
A4: 3 | B4: PM00003 | C4: O00130 | D4: -1 | E4: 139 | F4: Debit Card | G4: Failed | H4: 169639.44 | I4: =FALSE() -> FALSE
A5: 4 | B5: PM00004 | C5: O00137 | D5: 20241215 | E5: 60 | F5: Debit Card | G5: Success | H5: 84945.76 | I5: =FALSE() -> FALSE
A6: 5 | B6: PM00005 | C6: O00265 | D6: 20251020 | E6: 25 | F6: Netbanking | G6: Success | H6: 66656.86 | I6: =FALSE() -> FALSE
A7: 6 | B7: PM00006 | C7: O00221 | D7: 20241211 | E7: 70 | F7: Cod | G7: Success | H7: 121814.2 | I7: =FALSE() -> FALSE
A8: 7 | B8: PM00007 | C8: O00247 | D8: 20250401 | E8: -1 | F8: Cod | G8: Success | H8: 111449.1 | I8: =FALSE() -> FALSE
A9: 8 | B9: PM00008 | C9: O00077 | D9: 20240728 | E9: 3 | F9: Cod | G9: Failed | H9: 109161.52 | I9: =FALSE() -> FALSE
A10: 9 | B10: PM00009 | C10: O00126 | D10: 20240804 | E10: 29 | F10: Netbanking | G10: Pending | H10: 25721.45 | I10: =FALSE() -> FALSE
A11: 10 | B11: PM00010 | C11: O00230 | D11: -1 | E11: 70 | F11: Netbanking | G11: Failed | H11: 232807.42 | I11: =FALSE() -> FALSE
A12: 11 | B12: PM00011 | C12: O00272 | D12: 20240129 | E12: 121 | F12: Netbanking | G12: Success | H12: 85404.43 | I12: =FALSE() -> FALSE
A13: 12 | B13: PM00012 | C13: O00254 | D13: 20250920 | E13: 88 | F13: Cod | G13: Success | H13: 116934.61 | I13: =FALSE() -> FALSE
... A26: 25 | B26: PM00025 | C26: O00211 | D26: 20240321 | E26: 112 | F26: Netbanking | G26: Success | H26: 33891.3 | I26: =FALSE() -> FALSE
A27: 26 | B27: PM00026 | C27: O94535 | D27: 20250612 | E27: -1 | F27: Cod | G27: Refunded | H27: 45226.39 | I27: =TRUE() -> TRUE
A28: 27 | B28: PM00027 | C28: O00180 | D28: 20240601 | E28: 42 | F28: Debit Card | G28: Refunded | H28: 85251.43 | I28: =FALSE() -> FALSE
A29: 28 | B29: PM00028 | C29: O00143 | D29: 20240129 | E29: 129 | F29: Credit Card | G29: Success | H29: 82730.34 | I29: =FALSE() -> FALSE
A30: 29 | B30: PM00029 | C30: O00153 | D30: 20250608 | E30: 65 | F30: Credit Card | G30: Refunded | H30: 21122.18 | I30: =FALSE() -> FALSE
A31: 30 | B31: PM00030 | C31: O00099 | D31: 20241114 | E31: 65 | F31: Netbanking | G31: Failed | H31: 47190.36 | I31: =FALSE() -> FALSE
A32: 31 | B32: PM00031 | C32: O00089 | D32: 20250203 | E32: 67 | F32: Credit Card | G32: Success | H32: 20278.89 | I32: =FALSE() -> FALSE
A33: 32 | B33: PM00032 | C33: O00102 | D33: 20240509 | E33: -1 | F33: Cod | G33: Success | H33: 179805.82 | I33: =FALSE() -> FALSE
A34: 33 | B34: PM00033 | C34: O00127 | D34: 20240229 | E34: -1 | F34: Debit Card | G34: Success | H34: 78658.69 | I34: =FALSE() -> FALSE
A35: 34 | B35: PM00034 | C35: O00075 | D35: 20240415 | E35: 29 | F35: Credit Card | G35: Refunded | H35: 105538.37 | I35: =FALSE() -> FALSE
A36: 35 | B36: PM00035 | C36: O00104 | D36: 20240302 | E36: 117 | F36: Debit Card | G36: Success | H36: 131635.23 | I36: =FALSE() -> FALSE
A37: 36 | B37: PM00036 | C37: O00279 | D37: 20250218 | E37: 54 | F37: Debit Card | G37: Success | H37: 118038.32 | I37: =FALSE() -> FALSE
A38: 37 | B38: PM00037 | C38: O00117 | D38: 20250915 | E38: 45 | F38: Upi | G38: Pending | H38: 136297.54 | I38: =FALSE() -> FALSE
A39: 38 | B39: PM00038 | C39: O00042 | D39: 20251029 | E39: 78 | F39: Upi | G39: Success | H39: 27686.04 | I39: =FALSE() -> FALSE
... A125: 124 | B125: PM00124 | C125: O00173 | D125: 20240217 | E125: 146 | F125: Debit Card | G125: Success | H125: 110211.66 | I125: =FALSE() -> FALSE
A126: 125 | B126: PM00125 | C126: O93042 | D126: 20240722 | E126: -1 | F126: Cod | G126: Success | H126: 104461.04 | I126: =TRUE() -> TRUE
A127: 126 | B127: PM00126 | C127: O00204 | D127: 20250924 | E127: 13 | F127: Upi | G127: Failed | H127: 61320.42 | I127: =FALSE() -> FALSE
A128: 127 | B128: PM00127 | C128: O00086 | D128: 20251005 | E128: 129 | F128: Netbanking | G128: Success | H128: 113750.26 | I128: =FALSE() -> FALSE
A129: 128 | B129: PM00128 | C129: O00201 | D129: 20240603 | E129: 20 | F129: Debit Card | G129: Pending | H129: 86345.86 | I129: =FALSE() -> FALSE
A130: 129 | B130: PM00129 | C130: O00054 | D130: 20250430 | E130: 67 | F130: Debit Card | G130: Success | H130: 154521.63 | I130: =FALSE() -> FALSE
A131: 130 | B131: PM00130 | C131: O00195 | D131: 20241222 | E131: 107 | F131: Credit Card | G131: Success | H131: 217241.53 | I131: =FALSE() -> FALSE
A132: 131 | B132: PM00131 | C132: O00277 | D132: 20240506 | E132: 41 | F132: Credit Card | G132: Pending | H132: 48722.03 | I132: =FALSE() -> FALSE
A133: 132 | B133: PM00132 | C133: O00027 | D133: 20241218 | E133: 6 | F133: Cod | G133: Success | H133: 58166.47 | I133: =FALSE() -> FALSE
A134: 133 | B134: PM00133 | C134: O00093 | D134: 20240615 | E134: 103 | F134: Credit Card | G134: Success | H134: 16201.73 | I134: =FALSE() -> FALSE
A135: 134 | B135: PM00134 | C135: O00090 | D135: 20250222 | E135: 82 | F135: Cod | G135: Success | H135: 139080.17 | I135: =FALSE() -> FALSE
A136: 135 | B136: PM00135 | C136: O00133 | D136: 20240429 | E136: 154 | F136: Upi | G136: Success | H136: 70612.09 | I136: =FALSE() -> FALSE
A137: 136 | B137: PM00136 | C137: O00003 | D137: 20250516 | E137: 132 | F137: Cod | G137: Pending | H137: 33974.88 | I137: =FALSE() -> FALSE
A138: 137 | B138: PM00137 | C138: O00261 | D138: 20240510 | E138: 21 | F138: Netbanking | G138: Success | H138: 20632.4 | I138: =FALSE() -> FALSE
... A156: 155 | B156: PM00155 | C156: O00129 | D156: 20240609 | E156: 151 | F156: Credit Card | G156: Success | H156: 114760.35 | I156: =FALSE() -> FALSE
A157: 156 | B157: PM00156 | C157: O97748 | D157: 20250527 | E157: -1 | F157: Upi | G157: Success | H157: 107279.68 | I157: =TRUE() -> TRUE
A158: 157 | B158: PM00157 | C158: O00078 | D158: 20241015 | E158: 144 | F158: Cod | G158: Success | H158: 142183.2 | I158: =FALSE() -> FALSE
A159: 158 | B159: PM00158 | C159: O00016 | D159: 20250501 | E159: 36 | F159: Cod | G159: Refunded | H159: 80420.7 | I159: =FALSE() -> FALSE
A160: 159 | B160: PM00159 | C160: O00200 | D160: 20250211 | E160: 33 | F160: Upi | G160: Success | H160: 333060.9 | I160: =FALSE() -> FALSE
A161: 160 | B161: PM00160 | C161: O00299 | D161: 20251201 | E161: 31 | F161: Credit Card | G161: Success | H161: 134717.53 | I161: =FALSE() -> FALSE
A162: 161 | B162: PM00161 | C162: O00108 | D162: 20240523 | E162: 129 | F162: Netbanking | G162: Success | H162: 113386.32 | I162: =FALSE() -> FALSE
A163: 162 | B163: PM00162 | C163: O00190 | D163: 20250528 | E163: 25 | F163: Credit Card | G163: Success | H163: 88587.15 | I163: =FALSE() -> FALSE
A164: 163 | B164: PM00163 | C164: O00152 | D164: 20250912 | E164: 109 | F164: Credit Card | G164: Success | H164: 179268.9 | I164: =FALSE() -> FALSE
A165: 164 | B165: PM00164 | C165: O00141 | D165: 20240619 | E165: 95 | F165: Credit Card | G165: Success | H165: 24000.92 | I165: =FALSE() -> FALSE
A166: 165 | B166: PM00165 | C166: O00297 | D166: 20250610 | E166: 60 | F166: Cod | G166: Success | H166: 203529.85 | I166: =FALSE() -> FALSE
A167: 166 | B167: PM00166 | C167: O00014 | D167: 20241026 | E167: 78 | F167: Netbanking | G167: Success | H167: 156502.06 | I167: =FALSE() -> FALSE
A168: 167 | B168: PM00167 | C168: O00028 | D168: 20240923 | E168: 77 | F168: Credit Card | G168: Success | H168: 67330.43 | I168: =FALSE() -> FALSE
A169: 168 | B169: PM00168 | C169: O00148 | D169: 20250105 | E169: 157 | F169: Credit Card | G169: Success | H169: 40210.35 | I169: =FALSE() -> FALSE
... A192: 191 | B192: PM00191 | C192: O00039 | D192: 20250627 | E192: 88 | F192: Credit Card | G192: Success | H192: 54738.31 | I192: =FALSE() -> FALSE
A193: 192 | B193: PM00192 | C193: O98217 | D193: 20240302 | E193: -1 | F193: Upi | G193: Refunded | H193: 124164.45 | I193: =TRUE() -> TRUE
A194: 193 | B194: PM00193 | C194: O00095 | D194: 20240924 | E194: 21 | F194: Debit Card | G194: Pending | H194: 133028.66 | I194: =FALSE() -> FALSE
A195: 194 | B195: PM00194 | C195: O00123 | D195: 20250906 | E195: 149 | F195: Debit Card | G195: Success | H195: 9301.18 | I195: =FALSE() -> FALSE
A196: 195 | B196: PM00195 | C196: O00302 | D196: 20250605 | E196: 148 | F196: Credit Card | G196: Success | H196: 152621.39 | I196: =FALSE() -> FALSE
A197: 196 | B197: PM00196 | C197: O00243 | D197: 20250429 | E197: 37 | F197: Cod | G197: Pending | H197: 218900.57 | I197: =FALSE() -> FALSE
A198: 197 | B198: PM00197 | C198: O00034 | D198: 20250615 | E198: 136 | F198: Cod | G198: Success | H198: 183981.11 | I198: =FALSE() -> FALSE
A199: 198 | B199: PM00198 | C199: O00184 | D199: 20240425 | E199: 13 | F199: Credit Card | G199: Success | H199: 117460.38 | I199: =FALSE() -> FALSE
A200: 199 | B200: PM00199 | C200: O00283 | D200: 20250707 | E200: 96 | F200: Cod | G200: Success | H200: 33387.11 | I200: =FALSE() -> FALSE
A201: 200 | B201: PM00200 | C201: O00053 | D201: 20250704 | E201: 64 | F201: Debit Card | G201: Pending | H201: 4010.91 | I201: =FALSE() -> FALSE
A202: 201 | B202: PM00201 | C202: O00225 | D202: 20250121 | E202: 66 | F202: Cod | G202: Refunded | H202: 12720.99 | I202: =FALSE() -> FALSE
A203: 202 | B203: PM00202 | C203: O00006 | D203: 20250831 | E203: 122 | F203: Cod | G203: Success | H203: 17880.99 | I203: =FALSE() -> FALSE
A204: 203 | B204: PM00203 | C204: O00085 | D204: 20250202 | E204: 45 | F204: Debit Card | G204: Refunded | H204: 217987.79 | I204: =FALSE() -> FALSE
A205: 204 | B205: PM00204 | C205: O00231 | D205: 20240720 | E205: 66 | F205: Credit Card | G205: Success | H205: 27808.29 | I205: =FALSE() -> FALSE
... A264: 263 | B264: PM00263 | C264: O00170 | D264: 20240117 | E264: 2 | F264: Debit Card | G264: Refunded | H264: 174448.4 | I264: =FALSE() -> FALSE
A265: 264 | B265: PM00264 | C265: O97158 | D265: 20240723 | E265: -1 | F265: Credit Card | G265: Success | H265: 27430.41 | I265: =TRUE() -> TRUE
A266: 265 | B266: PM00265 | C266: O00232 | D266: 20251023 | E266: 76 | F266: Upi | G266: Refunded | H266: 105508.34 | I266: =FALSE() -> FALSE
A267: 266 | B267: PM00266 | C267: O00159 | D267: 20250216 | E267: 92 | F267: Upi | G267: Success | H267: 15622.68 | I267: =FALSE() -> FALSE
A268: 267 | B268: PM00267 | C268: O00271 | D268: 20251025 | E268: 61 | F268: Debit Card | G268: Success | H268: 48851.28 | I268: =FALSE() -> FALSE
A269: 268 | B269: PM00268 | C269: O00105 | D269: 20241023 | E269: 108 | F269: Upi | G269: Success | H269: 44887.01 | I269: =FALSE() -> FALSE
A270: 269 | B270: PM00269 | C270: O00289 | D270: 20240407 | E270: 76 | F270: Cod | G270: Refunded | H270: 87528.81 | I270: =FALSE() -> FALSE
A271: 270 | B271: PM00270 | C271: O00064 | D271: 20240131 | E271: 154 | F271: Debit Card | G271: Pending | H271: 120536.64 | I271: =FALSE() -> FALSE
A272: 271 | B272: PM00271 | C272: O00197 | D272: 20250702 | E272: 10 | F272: Upi | G272: Success | H272: 86842.72 | I272: =FALSE() -> FALSE
A273: 272 | B273: PM00272 | C273: O00008 | D273: 20240513 | E273: 118 | F273: Credit Card | G273: Success | H273: 168821.36 | I273: =FALSE() -> FALSE
A274: 273 | B274: PM00273 | C274: O00206 | D274: 20240709 | E274: 71 | F274: Netbanking | G274: Failed | H274: 47971.68 | I274: =FALSE() -> FALSE
A275: 274 | B275: PM00274 | C275: O00234 | D275: 20250522 | E275: 37 | F275: Credit Card | G275: Success | H275: 45144.5 | I275: =FALSE() -> FALSE
A276: 275 | B276: PM00275 | C276: O00268 | D276: 20250725 | E276: 102 | F276: Credit Card | G276: Success | H276: 41583.31 | I276: =FALSE() -> FALSE
A277: 276 | B277: PM00276 | C277: O00092 | D277: 20240316 | E277: 81 | F277: Debit Card | G277: Refunded | H277: 38376.08 | I277: =FALSE() -> FALSE
A278: 277 | B278: PM00277 | C278: O94502 | D278: 20240206 | E278: -1 | F278: Cod | G278: Failed | H278: 107841.66 | I278: =TRUE() -> TRUE
A279: 278 | B279: PM00278 | C279: O00147 | D279: 20250927 | E279: 30 | F279: Credit Card | G279: Success | H279: 75190.71 | I279: =FALSE() -> FALSE
A280: 279 | B280: PM00279 | C280: O00305 | D280: 20251209 | E280: 118 | F280: Upi | G280: Failed | H280: 56711.33 | I280: =FALSE() -> FALSE
A281: 280 | B281: PM00280 | C281: O00233 | D281: 20250508 | E281: 78 | F281: Credit Card | G281: Success | H281: 89899.8 | I281: =FALSE() -> FALSE
A282: 281 | B282: PM00281 | C282: O00025 | D282: 20250703 | E282: 106 | F282: Debit Card | G282: Success | H282: 64052.43 | I282: =FALSE() -> FALSE
A283: 282 | B283: PM00282 | C283: O00045 | D283: 20241001 | E283: 114 | F283: Debit Card | G283: Success | H283: 39842.03 | I283: =FALSE() -> FALSE
A284: 283 | B284: PM00283 | C284: O00113 | D284: 20250904 | E284: 52 | F284: Debit Card | G284: Success | H284: 3774.98 | I284: =FALSE() -> FALSE
A285: 284 | B285: PM00284 | C285: O00259 | D285: 20240315 | E285: 149 | F285: Netbanking | G285: Success | H285: 18066.11 | I285: =FALSE() -> FALSE
A286: 285 | B286: PM00285 | C286: O00010 | D286: 20241028 | E286: 100 | F286: Netbanking | G286: Success | H286: 168178.45 | I286: =FALSE() -> FALSE
A287: 286 | B287: PM00286 | C287: O00245 | D287: 20240116 | E287: 61 | F287: Debit Card | G287: Success | H287: 134606.36 | I287: =FALSE() -> FALSE
A288: 287 | B288: PM00287 | C288: O00081 | D288: 20240520 | E288: 37 | F288: Upi | G288: Refunded | H288: 253734.17 | I288: =FALSE() -> FALSE
A289: 288 | B289: PM00288 | C289: O00223 | D289: 20241226 | E289: 108 | F289: Credit Card | G289: Success | H289: 132799.24 | I289: =FALSE() -> FALSE
A290: 289 | B290: PM00289 | C290: O00050 | D290: 20240516 | E290: 32 | F290: Cod | G290: Success | H290: 171095.52 | I290: =FALSE() -> FALSE
... A294: 293 | B294: PM00293 | C294: O00185 | D294: 20250504 | E294: 71 | F294: Netbanking | G294: Success | H294: 112048.58 | I294: =FALSE() -> FALSE
A295: 294 | B295: PM00294 | C295: O90749 | D295: 20240404 | E295: -1 | F295: Upi | G295: Success | H295: 224837.1 | I295: =TRUE() -> TRUE
A296: 295 | B296: PM00295 | C296: O00192 | D296: 20250413 | E296: 88 | F296: Cod | G296: Pending | H296: 13548.3 | I296: =FALSE() -> FALSE
A297: 296 | B297: PM00296 | C297: O00062 | D297: 20240113 | E297: 111 | F297: Cod | G297: Success | H297: 103988.9 | I297: =FALSE() -> FALSE
...

Sheet FACT_RETURNS
A1: fact_return_key | B1: return_id | C1: fact_order_key | D1: return_date_key | E1: return_reason | F1: return_status | G1: refund_amount | H1: return_before_order
A2: 1 | B2: R0001 | C2: 677 | D2: 20240115 | E2: Not As Described | F2: Rejected | G2: 3268.11 | H2: =TRUE() -> TRUE
A3: 2 | B3: R0002 | C3: 525 | D3: 20240618 | E3: Not As Described | F3: Approved | G3: 18753.51 | H3: =TRUE() -> TRUE
A4: 3 | B4: R0003 | C4: 729 | D4: 20241228 | E4: Not As Described | F4: Approved | G4: 40668.25 | H4: =FALSE() -> FALSE
A5: 4 | B5: R0004 | C5: 404 | D5: 20240816 | E5: Wrong Item | F5: Pending | G5: 47839.34 | H5: =TRUE() -> TRUE
A6: 5 | B6: R0005 | C6: 291 | D6: 20240926 | E6: Size Issue | F6: Rejected | H6: =TRUE() -> TRUE
A7: 6 | B7: R0006 | C7: 288 | D7: 20230101 | E7: Not As Described | F7: Approved | G7: 75816.05 | H7: =TRUE() -> TRUE
A8: 7 | B8: R0007 | C8: 643 | D8: 20240825 | E8: Wrong Item | F8: Approved | G8: 20423.44 | H8: =TRUE() -> TRUE
A9: 8 | B9: R0008 | C9: 138 | D9: 20240828 | E9: Not As Described | F9: Rejected | G9: 110787.58 | H9: =FALSE() -> FALSE
A10: 9 | B10: R0009 | C10: 150 | D10: 20250303 | E10: Damged | F10: Approved | G10: 17236.27 | H10: =TRUE() -> TRUE
A11: 10 | B11: R0011 | C11: 657 | D11: 20251031 | E11: Wrong Item | F11: Rejected | G11: 19412.51 | H11: =FALSE() -> FALSE
A12: 11 | B12: R0012 | C12: 689 | D12: 20241208 | E12: Size Issue | F12: Rejected | G12: 5659.73 | H12: =FALSE() -> FALSE
A13: 12 | B13: R0013 | C13: 82 | D13: 20230101 | E13: Not As Described | F13: Approved | G13: 62797.05 | H13: =TRUE() -> TRUE
A14: 13 | B14: R0014 | C14: 479 | D14: 20250304 | E14: Not As Described | F14: Pending | G14: 40241.54 | H14: =FALSE() -> FALSE
A15: 14 | B15: R0015 | C15: 178 | D15: 20250824 | E15: Size Issue | F15: Rejected | G15: 81985.66 | H15: =TRUE() -> TRUE
A16: 15 | B16: R0016 | C16: 470 | D16: 20250901 | E16: Defective | F16: Approved | G16: 59773.61 | H16: =FALSE() -> FALSE
A17: 16 | B17: R0017 | C17: 611 | D17: 20250711 | E17: Size Issue | F17: Approved | G17: 62001.57 | H17: =FALSE() -> FALSE
A18: 17 | B18: R0018 | C18: 505 | D18: 20240121 | E18: Wrong Item | F18: Approved | G18: 18739.92 | H18: =TRUE() -> TRUE
A19: 18 | B19: R0019 | C19: 290 | D19: 20250114 | E19: Not As Described | F19: Pending | H19: =TRUE() -> TRUE
A20: 19 | B20: R0020 | C20: 18 | D20: 20241007 | E20: Wrong Item | F20: Rejected | G20: 26892.27 | H20: =TRUE() -> TRUE
A21: 20 | B21: R0021 | C21: 608 | D21: 20230101 | E21: Defective | F21: Approved | G21: 23398.87 | H21: =TRUE() -> TRUE
A22: 21 | B22: R0022 | C22: 145 | D22: 20230101 | E22: Size Issue | F22: Rejected | G22: 63852.01 | H22: =TRUE() -> TRUE
A23: 22 | B23: R0024 | C23: 152 | D23: 20240103 | E23: Size Issue | F23: Rejected | G23: 48644.66 | H23: =TRUE() -> TRUE
A24: 23 | B24: R0025 | C24: 382 | D24: 20240918 | E24: Not As Described | F24: Approved | G24: 86054.34 | H24: =FALSE() -> FALSE
A25: 24 | B25: R0026 | C25: 292 | D25: 20251019 | E25: Size Issue | F25: Approved | G25: 60115.27 | H25: =FALSE() -> FALSE
A26: 25 | B26: R0027 | C26: 634 | D26: 20250222 | E26: Size Issue | F26: Pending | G26: 20843.86 | H26: =TRUE() -> TRUE
A27: 26 | B27: R0028 | C27: 712 | D27: 20250303 | E27: Wrong Item | F27: Pending | G27: 20262.14 | H27: =FALSE() -> FALSE
A28: 27 | B28: R0029 | C28: 2 | D28: 20240604 | E28: Not As Described | F28: Approved | G28: 41619.4 | H28: =FALSE() -> FALSE
A29: 28 | B29: R0030 | C29: 556 | D29: 20240613 | E29: Not As Described | F29: Approved | G29: 3762.23 | H29: =FALSE() -> FALSE
A30: 29 | B30: R0031 | C30: 467 | D30: 20240414 | E30: Wrong Item | F30: Rejected | G30: 14407.22 | H30: =TRUE() -> TRUE
A31: 30 | B31: R0032 | C31: 167 | D31: 20251025 | E31: Not As Described | F31: Approved | G31: 41664.34 | H31: =FALSE() -> FALSE
A32: 31 | B32: R0033 | C32: 52 | D32: 20250914 | E32: Defective | F32: Rejected | G32: 43021.01 | H32: =FALSE() -> FALSE
A33: 32 | B33: R0035 | C33: 444 | D33: 20250501 | E33: Not As Described | F33: Pending | G33: 20370.24 | H33: =TRUE() -> TRUE
A34: 33 | B34: R0036 | C34: 256 | D34: 20240521 | E34: Not As Described | F34: Approved | G34: 18739.4 | H34: =TRUE() -> TRUE
A35: 34 | B35: R0037 | C35: 691 | D35: 20240404 | E35: Defective | F35: Approved | G35: 20754.81 | H35: =TRUE() -> TRUE
A36: 35 | B36: R0038 | C36: 740 | D36: 20250501 | E36: Wrong Item | F36: Pending | G36: 34020.93 | H36: =FALSE() -> FALSE
A37: 36 | B37: R0039 | C37: 571 | D37: 20250107 | E37: Wrong Item | F37: Rejected | G37: 8500.09 | H37: =TRUE() -> TRUE
A38: 37 | B38: R0040 | C38: 17 | D38: 20250813 | E38: Size Issue | F38: Approved | G38: 108702.96 | H38: =FALSE() -> FALSE
A39: 38 | B39: R0041 | C39: 35 | D39: 20240730 | E39: Wrong Item | F39: Approved | G39: 34576.69 | H39: =TRUE() -> TRUE
A40: 39 | B40: R0042 | C40: 26 | D40: 20250427 | E40: Size Issue | F40: Approved | G40: 10324.63 | H40: =FALSE() -> FALSE
A41: 40 | B41: R0043 | C41: 79 | D41: 20241224 | E41: Size Issue | F41: Rejected | G41: 39878.02 | H41: =FALSE() -> FALSE
A42: 41 | B42: R0044 | C42: 618 | D42: 20240402 | E42: Wrong Item | F42: Rejected | G42: 25783.29 | H42: =TRUE() -> TRUE
A43: 42 | B43: R0045 | C43: 598 | D43: 20251211 | E43: Size Issue | F43: Approved | G43: 6474.73 | H43: =FALSE() -> FALSE
A44: 43 | B44: R0046 | C44: 113 | D44: 20251029 | E44: Wrong Item | F44: Approved | G44: 74184.94 | H44: =FALSE() -> FALSE
A45: 44 | B45: R0047 | C45: 757 | D45: 20240904 | E45: Defective | F45: Pending | G45: 63225.26 | H45: =FALSE() -> FALSE
A46: 45 | B46: R0049 | C46: 362 | D46: 20230101 | E46: Wrong Item | F46: Rejected | G46: 11703.26 | H46: =TRUE() -> TRUE
A47: 46 | B47: R0050 | C47: 619 | D47: 20240508 | E47: Wrong Item | F47: Rejected | G47: 9727.89 | H47: =TRUE() -> TRUE
A48: 47 | B48: R0051 | C48: 300 | D48: 20250116 | E48: Defective | F48: Approved | G48: 19128.89 | H48: =FALSE() -> FALSE
A49: 48 | B49: R0052 | C49: 201 | D49: 20251010 | E49: Wrong Item | F49: Rejected | G49: 8184.16 | H49: =TRUE() -> TRUE
A50: 49 | B50: R0053 | C50: 44 | D50: 20240321 | E50: Wrong Item | F50: Approved | H50: =TRUE() -> TRUE
A51: 50 | B51: R0054 | C51: 260 | D51: 20240508 | E51: Damged | F51: Approved | G51: 78750.76 | H51: =TRUE() -> TRUE
A52: 51 | B52: R0055 | C52: 84 | D52: 20250824 | E52: Damged | F52: Rejected | G52: 4429.86 | H52: =FALSE() -> FALSE
A53: 52 | B53: R0056 | C53: 305 | D53: 20251205 | E53: Size Issue | F53: Pending | G53: 10327.76 | H53: =FALSE() -> FALSE
A54: 53 | B54: R0057 | C54: 166 | D54: 20250607 | E54: Not As Described | F54: Rejected | G54: 4892.22 | H54: =FALSE() -> FALSE
A55: 54 | B55: R0058 | C55: 351 | D55: 20250825 | E55: Damged | F55: Rejected | G55: 74191.07 | H55: =FALSE() -> FALSE
A56: 55 | B56: R0059 | C56: 547 | D56: 20241010 | E56: Defective | F56: Approved | G56: 10420.55 | H56: =TRUE() -> TRUE
A57: 56 | B57: R0061 | C57: 481 | D57: 20241030 | E57: Size Issue | F57: Rejected | H57: =FALSE() -> FALSE
A58: 57 | B58: R0062 | C58: 761 | D58: 20250930 | E58: Not As Described | F58: Approved | G58: 59302.19 | H58: =FALSE() -> FALSE
A59: 58 | B59: R0063 | C59: 334 | D59: 20250309 | E59: Defective | F59: Rejected | G59: 13543.13 | H59: =FALSE() -> FALSE
A60: 59 | B60: R0064 | C60: 669 | D60: 20250930 | E60: Defective | F60: Approved | G60: 36219.09 | H60: =FALSE() -> FALSE
